{
"meta":{"test_sets":[],"test_metrics":[],"learn_metrics":[{"best_value":"Min","name":"RMSE"}],"launch_mode":"Train","parameters":"","iteration_count":1000,"learn_sets":["learn"],"name":"experiment"},
"iterations":[
{"learn":[14.48288304],"iteration":0,"passed_time":0.1288896197,"remaining_time":128.7607301},
{"learn":[14.10450297],"iteration":1,"passed_time":0.1306194224,"remaining_time":65.17909178},
{"learn":[13.75521755],"iteration":2,"passed_time":0.1320442194,"remaining_time":43.88269557},
{"learn":[13.39138698],"iteration":3,"passed_time":0.1334282965,"remaining_time":33.22364584},
{"learn":[13.05371583],"iteration":4,"passed_time":0.1348742485,"remaining_time":26.83997545},
{"learn":[12.75624228],"iteration":5,"passed_time":0.1362157066,"remaining_time":22.56640207},
{"learn":[12.45077287],"iteration":6,"passed_time":0.1381197528,"remaining_time":19.59327351},
{"learn":[12.18111203],"iteration":7,"passed_time":0.140384794,"remaining_time":17.40771446},
{"learn":[11.89589471],"iteration":8,"passed_time":0.1422034372,"remaining_time":15.65817848},
{"learn":[11.61623692],"iteration":9,"passed_time":0.1446742944,"remaining_time":14.32275515},
{"learn":[11.32998339],"iteration":10,"passed_time":0.1463668835,"remaining_time":13.15971344},
{"learn":[11.08921663],"iteration":11,"passed_time":0.1480135636,"remaining_time":12.18645007},
{"learn":[10.83839481],"iteration":12,"passed_time":0.1498944665,"remaining_time":11.38044911},
{"learn":[10.6003816],"iteration":13,"passed_time":0.1515628568,"remaining_time":10.67435548},
{"learn":[10.36190825],"iteration":14,"passed_time":0.1531624741,"remaining_time":10.05766913},
{"learn":[10.11929127],"iteration":15,"passed_time":0.1546122932,"remaining_time":9.508656031},
{"learn":[9.910953721],"iteration":16,"passed_time":0.1563632463,"remaining_time":9.041474772},
{"learn":[9.702668667],"iteration":17,"passed_time":0.1580220731,"remaining_time":8.620981988},
{"learn":[9.499047174],"iteration":18,"passed_time":0.1597205534,"remaining_time":8.246624365},
{"learn":[9.310121992],"iteration":19,"passed_time":0.1613037141,"remaining_time":7.903881993},
{"learn":[9.16962096],"iteration":20,"passed_time":0.1627407693,"remaining_time":7.586819673},
{"learn":[9.000421869],"iteration":21,"passed_time":0.1640417423,"remaining_time":7.292401091},
{"learn":[8.844523374],"iteration":22,"passed_time":0.165312329,"remaining_time":7.022180237},
{"learn":[8.676243482],"iteration":23,"passed_time":0.1667136479,"remaining_time":6.779688347},
{"learn":[8.526098058],"iteration":24,"passed_time":0.1680349289,"remaining_time":6.553362227},
{"learn":[8.38630217],"iteration":25,"passed_time":0.1692666936,"remaining_time":6.340990751},
{"learn":[8.253781137],"iteration":26,"passed_time":0.1706589559,"remaining_time":6.150043116},
{"learn":[8.125753043],"iteration":27,"passed_time":0.1718865729,"remaining_time":5.966919603},
{"learn":[8.007146642],"iteration":28,"passed_time":0.1735101043,"remaining_time":5.809596939},
{"learn":[7.885066867],"iteration":29,"passed_time":0.1748581643,"remaining_time":5.653747313},
{"learn":[7.783685515],"iteration":30,"passed_time":0.1761282,"remaining_time":5.505426639},
{"learn":[7.676200455],"iteration":31,"passed_time":0.1773205716,"remaining_time":5.363947291},
{"learn":[7.568509309],"iteration":32,"passed_time":0.1786385061,"remaining_time":5.234649558},
{"learn":[7.471828462],"iteration":33,"passed_time":0.1799863962,"remaining_time":5.113731139},
{"learn":[7.363318728],"iteration":34,"passed_time":0.1813936764,"remaining_time":5.001282792},
{"learn":[7.266926405],"iteration":35,"passed_time":0.1826380144,"remaining_time":4.890640163},
{"learn":[7.176147295],"iteration":36,"passed_time":0.1837712263,"remaining_time":4.783018673},
{"learn":[7.102594655],"iteration":37,"passed_time":0.1851901235,"remaining_time":4.688234179},
{"learn":[7.02305075],"iteration":38,"passed_time":0.1865277746,"remaining_time":4.596235676},
{"learn":[6.950958901],"iteration":39,"passed_time":0.1878745878,"remaining_time":4.508990107},
{"learn":[6.870367229],"iteration":40,"passed_time":0.1892409263,"remaining_time":4.426391423},
{"learn":[6.79242498],"iteration":41,"passed_time":0.1906695261,"remaining_time":4.349081095},
{"learn":[6.722982699],"iteration":42,"passed_time":0.1926816385,"remaining_time":4.288286698},
{"learn":[6.664793057],"iteration":43,"passed_time":0.1940344331,"remaining_time":4.215839046},
{"learn":[6.601276964],"iteration":44,"passed_time":0.196963641,"remaining_time":4.18000616},
{"learn":[6.545419099],"iteration":45,"passed_time":0.1989760294,"remaining_time":4.126589827},
{"learn":[6.484448184],"iteration":46,"passed_time":0.2005421384,"remaining_time":4.066311871},
{"learn":[6.428488082],"iteration":47,"passed_time":0.202048623,"remaining_time":4.007297689},
{"learn":[6.373355815],"iteration":48,"passed_time":0.2044760107,"remaining_time":3.9685038},
{"learn":[6.323124238],"iteration":49,"passed_time":0.2059944672,"remaining_time":3.913894876},
{"learn":[6.276635241],"iteration":50,"passed_time":0.2075545511,"remaining_time":3.86214253},
{"learn":[6.234194801],"iteration":51,"passed_time":0.2105815608,"remaining_time":3.839063839},
{"learn":[6.186920865],"iteration":52,"passed_time":0.2129297763,"remaining_time":3.804613172},
{"learn":[6.14305064],"iteration":53,"passed_time":0.2177908322,"remaining_time":3.815372728},
{"learn":[6.097612094],"iteration":54,"passed_time":0.2209390913,"remaining_time":3.796135297},
{"learn":[6.061869657],"iteration":55,"passed_time":0.2225553492,"remaining_time":3.751647315},
{"learn":[6.020275531],"iteration":56,"passed_time":0.2245062477,"remaining_time":3.714199852},
{"learn":[5.989740425],"iteration":57,"passed_time":0.2260241628,"remaining_time":3.670944162},
{"learn":[5.956483673],"iteration":58,"passed_time":0.2300536467,"remaining_time":3.669160704},
{"learn":[5.925845032],"iteration":59,"passed_time":0.2328832007,"remaining_time":3.648503478},
{"learn":[5.897642061],"iteration":60,"passed_time":0.234773747,"remaining_time":3.613976204},
{"learn":[5.867273795],"iteration":61,"passed_time":0.2361555299,"remaining_time":3.57280463},
{"learn":[5.837797976],"iteration":62,"passed_time":0.2373813937,"remaining_time":3.530577236},
{"learn":[5.808213899],"iteration":63,"passed_time":0.2389449538,"remaining_time":3.494569949},
{"learn":[5.778189623],"iteration":64,"passed_time":0.2407015519,"remaining_time":3.462399247},
{"learn":[5.750776775],"iteration":65,"passed_time":0.2427242236,"remaining_time":3.434915527},
{"learn":[5.726499081],"iteration":66,"passed_time":0.2448022282,"remaining_time":3.408962371},
{"learn":[5.700628144],"iteration":67,"passed_time":0.2476338952,"remaining_time":3.394041034},
{"learn":[5.675571432],"iteration":68,"passed_time":0.2490512046,"remaining_time":3.360386543},
{"learn":[5.648502795],"iteration":69,"passed_time":0.2504978272,"remaining_time":3.328042561},
{"learn":[5.628039957],"iteration":70,"passed_time":0.25191742,"remaining_time":3.296215256},
{"learn":[5.605420306],"iteration":71,"passed_time":0.253182552,"remaining_time":3.263241781},
{"learn":[5.588479511],"iteration":72,"passed_time":0.2544481342,"remaining_time":3.231142746},
{"learn":[5.568869282],"iteration":73,"passed_time":0.255767822,"remaining_time":3.200554097},
{"learn":[5.553841129],"iteration":74,"passed_time":0.2572025228,"remaining_time":3.172164448},
{"learn":[5.537117251],"iteration":75,"passed_time":0.2589110973,"remaining_time":3.147813867},
{"learn":[5.521127423],"iteration":76,"passed_time":0.2604291126,"remaining_time":3.121767155},
{"learn":[5.501743483],"iteration":77,"passed_time":0.2617971303,"remaining_time":3.094576335},
{"learn":[5.481955834],"iteration":78,"passed_time":0.2633237018,"remaining_time":3.069887713},
{"learn":[5.464782751],"iteration":79,"passed_time":0.2646317786,"remaining_time":3.043265454},
{"learn":[5.450477791],"iteration":80,"passed_time":0.2659049947,"remaining_time":3.016872718},
{"learn":[5.43960285],"iteration":81,"passed_time":0.2669459904,"remaining_time":2.988492917},
{"learn":[5.423301901],"iteration":82,"passed_time":0.2683235057,"remaining_time":2.964489816},
{"learn":[5.410336002],"iteration":83,"passed_time":0.2696805628,"remaining_time":2.940802328},
{"learn":[5.396724101],"iteration":84,"passed_time":0.2710362376,"remaining_time":2.917625381},
{"learn":[5.383443002],"iteration":85,"passed_time":0.2728511035,"remaining_time":2.899836147},
{"learn":[5.370703866],"iteration":86,"passed_time":0.2747778831,"remaining_time":2.883588589},
{"learn":[5.360162579],"iteration":87,"passed_time":0.2773148729,"remaining_time":2.873990501},
{"learn":[5.347062125],"iteration":88,"passed_time":0.278853076,"remaining_time":2.854327553},
{"learn":[5.335687871],"iteration":89,"passed_time":0.2802065464,"remaining_time":2.833199525},
{"learn":[5.327291886],"iteration":90,"passed_time":0.2821967078,"remaining_time":2.818866015},
{"learn":[5.318304597],"iteration":91,"passed_time":0.2836564553,"remaining_time":2.799565885},
{"learn":[5.30724762],"iteration":92,"passed_time":0.2851719462,"remaining_time":2.781193067},
{"learn":[5.297779423],"iteration":93,"passed_time":0.2867223677,"remaining_time":2.763515587},
{"learn":[5.289633793],"iteration":94,"passed_time":0.2881414095,"remaining_time":2.744926059},
{"learn":[5.277509004],"iteration":95,"passed_time":0.2896174572,"remaining_time":2.727231056},
{"learn":[5.267788535],"iteration":96,"passed_time":0.2910161916,"remaining_time":2.709150732},
{"learn":[5.259505016],"iteration":97,"passed_time":0.2922575441,"remaining_time":2.689962293},
{"learn":[5.253106665],"iteration":98,"passed_time":0.2940043844,"remaining_time":2.675736872},
{"learn":[5.240584566],"iteration":99,"passed_time":0.2956636623,"remaining_time":2.660972961},
{"learn":[5.233308482],"iteration":100,"passed_time":0.2970445132,"remaining_time":2.643990271},
{"learn":[5.225541061],"iteration":101,"passed_time":0.2987117559,"remaining_time":2.629834871},
{"learn":[5.216553593],"iteration":102,"passed_time":0.300930957,"remaining_time":2.620728819},
{"learn":[5.20784455],"iteration":103,"passed_time":0.3025946227,"remaining_time":2.606969057},
{"learn":[5.200774446],"iteration":104,"passed_time":0.3040848216,"remaining_time":2.591961099},
{"learn":[5.195110629],"iteration":105,"passed_time":0.3054011932,"remaining_time":2.575742139},
{"learn":[5.186595495],"iteration":106,"passed_time":0.3069762546,"remaining_time":2.561960705},
{"learn":[5.180138188],"iteration":107,"passed_time":0.3083506639,"remaining_time":2.546748076},
{"learn":[5.174337738],"iteration":108,"passed_time":0.309559486,"remaining_time":2.530435799},
{"learn":[5.166919227],"iteration":109,"passed_time":0.3107872132,"remaining_time":2.514551089},
{"learn":[5.1596801],"iteration":110,"passed_time":0.3125298955,"remaining_time":2.503054749},
{"learn":[5.153593727],"iteration":111,"passed_time":0.313803568,"remaining_time":2.488014003},
{"learn":[5.14881088],"iteration":112,"passed_time":0.3151095703,"remaining_time":2.473470698},
{"learn":[5.144331523],"iteration":113,"passed_time":0.3164277353,"remaining_time":2.459254153},
{"learn":[5.135151614],"iteration":114,"passed_time":0.3180283341,"remaining_time":2.44743544},
{"learn":[5.129169768],"iteration":115,"passed_time":0.3198629827,"remaining_time":2.437576523},
{"learn":[5.121714149],"iteration":116,"passed_time":0.3210267312,"remaining_time":2.422791484},
{"learn":[5.116247936],"iteration":117,"passed_time":0.3222037043,"remaining_time":2.408336163},
{"learn":[5.11118286],"iteration":118,"passed_time":0.3233649081,"remaining_time":2.393987261},
{"learn":[5.103790802],"iteration":119,"passed_time":0.325183245,"remaining_time":2.38467713},
{"learn":[5.096303826],"iteration":120,"passed_time":0.3265582253,"remaining_time":2.372270083},
{"learn":[5.091804532],"iteration":121,"passed_time":0.3278199155,"remaining_time":2.359228572},
{"learn":[5.083199037],"iteration":122,"passed_time":0.3292398692,"remaining_time":2.347507035},
{"learn":[5.078218092],"iteration":123,"passed_time":0.3310170813,"remaining_time":2.33847551},
{"learn":[5.072481389],"iteration":124,"passed_time":0.332585396,"remaining_time":2.328097772},
{"learn":[5.0668582],"iteration":125,"passed_time":0.3339240189,"remaining_time":2.316266607},
{"learn":[5.062181177],"iteration":126,"passed_time":0.3352048491,"remaining_time":2.304203412},
{"learn":[5.058191076],"iteration":127,"passed_time":0.3369625493,"remaining_time":2.295557367},
{"learn":[5.054584408],"iteration":128,"passed_time":0.338442174,"remaining_time":2.28514057},
{"learn":[5.050604402],"iteration":129,"passed_time":0.3396667651,"remaining_time":2.273154505},
{"learn":[5.045959273],"iteration":130,"passed_time":0.3409549948,"remaining_time":2.261754889},
{"learn":[5.040810872],"iteration":131,"passed_time":0.3429265814,"remaining_time":2.255002066},
{"learn":[5.031332415],"iteration":132,"passed_time":0.3443697883,"remaining_time":2.24487674},
{"learn":[5.026428598],"iteration":133,"passed_time":0.3456214999,"remaining_time":2.233643425},
{"learn":[5.021782041],"iteration":134,"passed_time":0.3468829797,"remaining_time":2.222620574},
{"learn":[5.016939851],"iteration":135,"passed_time":0.3481416042,"remaining_time":2.211723133},
{"learn":[5.013071769],"iteration":136,"passed_time":0.3495164242,"remaining_time":2.201698351},
{"learn":[5.005585882],"iteration":137,"passed_time":0.3509281227,"remaining_time":2.192029288},
{"learn":[4.999679741],"iteration":138,"passed_time":0.3522107617,"remaining_time":2.18167961},
{"learn":[4.996303545],"iteration":139,"passed_time":0.3535849906,"remaining_time":2.172022085},
{"learn":[4.992000145],"iteration":140,"passed_time":0.3554048261,"remaining_time":2.165196777},
{"learn":[4.986403165],"iteration":141,"passed_time":0.35698126,"remaining_time":2.156971275},
{"learn":[4.980256126],"iteration":142,"passed_time":0.3584222179,"remaining_time":2.148026858},
{"learn":[4.973520398],"iteration":143,"passed_time":0.3599115099,"remaining_time":2.139473976},
{"learn":[4.96912397],"iteration":144,"passed_time":0.3613861602,"remaining_time":2.130932186},
{"learn":[4.963603976],"iteration":145,"passed_time":0.3627918876,"remaining_time":2.122084055},
{"learn":[4.958251252],"iteration":146,"passed_time":0.3640575451,"remaining_time":2.112524395},
{"learn":[4.955318594],"iteration":147,"passed_time":0.3652502774,"remaining_time":2.102657002},
{"learn":[4.949551436],"iteration":148,"passed_time":0.3664759808,"remaining_time":2.09309436},
{"learn":[4.946171257],"iteration":149,"passed_time":0.3679216122,"remaining_time":2.084889136},
{"learn":[4.941602549],"iteration":150,"passed_time":0.3691596686,"remaining_time":2.075606348},
{"learn":[4.940111415],"iteration":151,"passed_time":0.3705225816,"remaining_time":2.067125982},
{"learn":[4.937946171],"iteration":152,"passed_time":0.3717257533,"remaining_time":2.057854334},
{"learn":[4.934546101],"iteration":153,"passed_time":0.3729892419,"remaining_time":2.049018823},
{"learn":[4.928423945],"iteration":154,"passed_time":0.3742804517,"remaining_time":2.04043214},
{"learn":[4.924026455],"iteration":155,"passed_time":0.3754852364,"remaining_time":2.031471407},
{"learn":[4.918544584],"iteration":156,"passed_time":0.3767051992,"remaining_time":2.022690974},
{"learn":[4.912958841],"iteration":157,"passed_time":0.3779240098,"remaining_time":2.014000103},
{"learn":[4.909662898],"iteration":158,"passed_time":0.3795419656,"remaining_time":2.007514422},
{"learn":[4.9031679],"iteration":159,"passed_time":0.3808186236,"remaining_time":1.999297774},
{"learn":[4.897498475],"iteration":160,"passed_time":0.382000666,"remaining_time":1.990674278},
{"learn":[4.894782567],"iteration":161,"passed_time":0.3831362423,"remaining_time":1.98190229},
{"learn":[4.89108418],"iteration":162,"passed_time":0.384311963,"remaining_time":1.973430141},
{"learn":[4.887497673],"iteration":163,"passed_time":0.3855688243,"remaining_time":1.965460592},
{"learn":[4.881304518],"iteration":164,"passed_time":0.3868815843,"remaining_time":1.95785529},
{"learn":[4.875620448],"iteration":165,"passed_time":0.3881557176,"remaining_time":1.950131738},
{"learn":[4.872768132],"iteration":166,"passed_time":0.3893230427,"remaining_time":1.941952662},
{"learn":[4.869201069],"iteration":167,"passed_time":0.3904695894,"remaining_time":1.933754157},
{"learn":[4.861969648],"iteration":168,"passed_time":0.3919446602,"remaining_time":1.927254512},
{"learn":[4.85997435],"iteration":169,"passed_time":0.3932860281,"remaining_time":1.920161196},
{"learn":[4.856676065],"iteration":170,"passed_time":0.3944840703,"remaining_time":1.912440317},
{"learn":[4.854766363],"iteration":171,"passed_time":0.3956523572,"remaining_time":1.904652045},
{"learn":[4.852655633],"iteration":172,"passed_time":0.3968000056,"remaining_time":1.896841645},
{"learn":[4.848860494],"iteration":173,"passed_time":0.3985296237,"remaining_time":1.891870512},
{"learn":[4.848167791],"iteration":174,"passed_time":0.3996716519,"remaining_time":1.884166359},
{"learn":[4.841439073],"iteration":175,"passed_time":0.4008262234,"remaining_time":1.8765955},
{"learn":[4.837330076],"iteration":176,"passed_time":0.4020011827,"remaining_time":1.86919194},
{"learn":[4.832866355],"iteration":177,"passed_time":0.4031987837,"remaining_time":1.861962923},
{"learn":[4.830464905],"iteration":178,"passed_time":0.4046198198,"remaining_time":1.855826101},
{"learn":[4.827662918],"iteration":179,"passed_time":0.4058427477,"remaining_time":1.848839184},
{"learn":[4.824142486],"iteration":180,"passed_time":0.4071322495,"remaining_time":1.842217195},
{"learn":[4.819211136],"iteration":181,"passed_time":0.4083070485,"remaining_time":1.835138273},
{"learn":[4.814855328],"iteration":182,"passed_time":0.4095216414,"remaining_time":1.828301535},
{"learn":[4.811858327],"iteration":183,"passed_time":0.4107435077,"remaining_time":1.821558164},
{"learn":[4.809797456],"iteration":184,"passed_time":0.4119074265,"remaining_time":1.814619203},
{"learn":[4.804465593],"iteration":185,"passed_time":0.4130228654,"remaining_time":1.807530175},
{"learn":[4.80089318],"iteration":186,"passed_time":0.4141534524,"remaining_time":1.800570892},
{"learn":[4.793491181],"iteration":187,"passed_time":0.4153067917,"remaining_time":1.793771887},
{"learn":[4.788851526],"iteration":188,"passed_time":0.4165644744,"remaining_time":1.787480364},
{"learn":[4.785477952],"iteration":189,"passed_time":0.4177690286,"remaining_time":1.781015333},
{"learn":[4.782503614],"iteration":190,"passed_time":0.4189230591,"remaining_time":1.774391387},
{"learn":[4.779717564],"iteration":191,"passed_time":0.4200715594,"remaining_time":1.767801146},
{"learn":[4.777185725],"iteration":192,"passed_time":0.4212107924,"remaining_time":1.761228546},
{"learn":[4.773357457],"iteration":193,"passed_time":0.4224280201,"remaining_time":1.755036001},
{"learn":[4.768244893],"iteration":194,"passed_time":0.4237586382,"remaining_time":1.749362583},
{"learn":[4.765913657],"iteration":195,"passed_time":0.4249336676,"remaining_time":1.743095249},
{"learn":[4.762623424],"iteration":196,"passed_time":0.4260798335,"remaining_time":1.736761961},
{"learn":[4.759799312],"iteration":197,"passed_time":0.4271911247,"remaining_time":1.730339808},
{"learn":[4.75605763],"iteration":198,"passed_time":0.4286703487,"remaining_time":1.725452007},
{"learn":[4.750098882],"iteration":199,"passed_time":0.4300175575,"remaining_time":1.72007023},
{"learn":[4.744717539],"iteration":200,"passed_time":0.4312241755,"remaining_time":1.714169733},
{"learn":[4.743983217],"iteration":201,"passed_time":0.4323868718,"remaining_time":1.708142197},
{"learn":[4.740526617],"iteration":202,"passed_time":0.4335214963,"remaining_time":1.702052377},
{"learn":[4.734852167],"iteration":203,"passed_time":0.4348199847,"remaining_time":1.696650529},
{"learn":[4.72946632],"iteration":204,"passed_time":0.4360528715,"remaining_time":1.691034307},
{"learn":[4.726370137],"iteration":205,"passed_time":0.4371724982,"remaining_time":1.685024095},
{"learn":[4.71974724],"iteration":206,"passed_time":0.4383364371,"remaining_time":1.679230892},
{"learn":[4.714013766],"iteration":207,"passed_time":0.4396213761,"remaining_time":1.673942932},
{"learn":[4.713219926],"iteration":208,"passed_time":0.4410268078,"remaining_time":1.669149306},
{"learn":[4.711989414],"iteration":209,"passed_time":0.442203901,"remaining_time":1.663528961},
{"learn":[4.708507765],"iteration":210,"passed_time":0.4433502072,"remaining_time":1.657835609},
{"learn":[4.704468893],"iteration":211,"passed_time":0.4445749389,"remaining_time":1.65247666},
{"learn":[4.69972284],"iteration":212,"passed_time":0.4459187514,"remaining_time":1.647596513},
{"learn":[4.696836826],"iteration":213,"passed_time":0.4472572139,"remaining_time":1.642729767},
{"learn":[4.695697314],"iteration":214,"passed_time":0.4484265027,"remaining_time":1.637278161},
{"learn":[4.693024736],"iteration":215,"passed_time":0.449637028,"remaining_time":1.632015879},
{"learn":[4.689137124],"iteration":216,"passed_time":0.4508195013,"remaining_time":1.626689721},
{"learn":[4.688520981],"iteration":217,"passed_time":0.4521727215,"remaining_time":1.622014074},
{"learn":[4.685578041],"iteration":218,"passed_time":0.4535526207,"remaining_time":1.617463912},
{"learn":[4.680562704],"iteration":219,"passed_time":0.4548949456,"remaining_time":1.612809352},
{"learn":[4.674968982],"iteration":220,"passed_time":0.4562003775,"remaining_time":1.608054724},
{"learn":[4.670715326],"iteration":221,"passed_time":0.4574800009,"remaining_time":1.603240724},
{"learn":[4.665823319],"iteration":222,"passed_time":0.4588586584,"remaining_time":1.598803487},
{"learn":[4.662735597],"iteration":223,"passed_time":0.4603678327,"remaining_time":1.594845706},
{"learn":[4.661039062],"iteration":224,"passed_time":0.4619569854,"remaining_time":1.591185172},
{"learn":[4.658405021],"iteration":225,"passed_time":0.4633100651,"remaining_time":1.586734471},
{"learn":[4.655487487],"iteration":226,"passed_time":0.4648445112,"remaining_time":1.582928666},
{"learn":[4.654996802],"iteration":227,"passed_time":0.4661850574,"remaining_time":1.578486247},
{"learn":[4.652013391],"iteration":228,"passed_time":0.4673931281,"remaining_time":1.573624899},
{"learn":[4.649418349],"iteration":229,"passed_time":0.4687553499,"remaining_time":1.569311389},
{"learn":[4.648573881],"iteration":230,"passed_time":0.4702085101,"remaining_time":1.565326166},
{"learn":[4.64756389],"iteration":231,"passed_time":0.4716087825,"remaining_time":1.561187694},
{"learn":[4.645075697],"iteration":232,"passed_time":0.4728294766,"remaining_time":1.556481582},
{"learn":[4.643053592],"iteration":233,"passed_time":0.4740751871,"remaining_time":1.551887151},
{"learn":[4.640065506],"iteration":234,"passed_time":0.4752347279,"remaining_time":1.54704071},
{"learn":[4.639187721],"iteration":235,"passed_time":0.4766013175,"remaining_time":1.54289579},
{"learn":[4.632487944],"iteration":236,"passed_time":0.4779704421,"remaining_time":1.538782478},
{"learn":[4.631634943],"iteration":237,"passed_time":0.4791538771,"remaining_time":1.534097707},
{"learn":[4.62728999],"iteration":238,"passed_time":0.4803573193,"remaining_time":1.529505941},
{"learn":[4.625004025],"iteration":239,"passed_time":0.4816087152,"remaining_time":1.525094265},
{"learn":[4.620311576],"iteration":240,"passed_time":0.4830515216,"remaining_time":1.521311639},
{"learn":[4.614346389],"iteration":241,"passed_time":0.4844985556,"remaining_time":1.517561591},
{"learn":[4.609857671],"iteration":242,"passed_time":0.4856968582,"remaining_time":1.513055645},
{"learn":[4.606432663],"iteration":243,"passed_time":0.4869664278,"remaining_time":1.508797621},
{"learn":[4.600474898],"iteration":244,"passed_time":0.4883560553,"remaining_time":1.504933966},
{"learn":[4.594187125],"iteration":245,"passed_time":0.4900345938,"remaining_time":1.50197595},
{"learn":[4.593569829],"iteration":246,"passed_time":0.4913635588,"remaining_time":1.49796259},
{"learn":[4.591595699],"iteration":247,"passed_time":0.4929918289,"remaining_time":1.494878449},
{"learn":[4.588650522],"iteration":248,"passed_time":0.4951474623,"remaining_time":1.493396563},
{"learn":[4.584796618],"iteration":249,"passed_time":0.4967345709,"remaining_time":1.490203713},
{"learn":[4.579862168],"iteration":250,"passed_time":0.4979316012,"remaining_time":1.485859639},
{"learn":[4.579432933],"iteration":251,"passed_time":0.499139151,"remaining_time":1.481571766},
{"learn":[4.57874405],"iteration":252,"passed_time":0.500361929,"remaining_time":1.477353205},
{"learn":[4.577413998],"iteration":253,"passed_time":0.5017148283,"remaining_time":1.473540401},
{"learn":[4.574723168],"iteration":254,"passed_time":0.5029824947,"remaining_time":1.469497877},
{"learn":[4.570973244],"iteration":255,"passed_time":0.5041783428,"remaining_time":1.465268309},
{"learn":[4.566695594],"iteration":256,"passed_time":0.5054280307,"remaining_time":1.461218003},
{"learn":[4.566022768],"iteration":257,"passed_time":0.5067778091,"remaining_time":1.457477265},
{"learn":[4.564997349],"iteration":258,"passed_time":0.5080813819,"remaining_time":1.453622795},
{"learn":[4.559851878],"iteration":259,"passed_time":0.5094064296,"remaining_time":1.449849069},
{"learn":[4.559147445],"iteration":260,"passed_time":0.5105634857,"remaining_time":1.445618452},
{"learn":[4.554971219],"iteration":261,"passed_time":0.5120887648,"remaining_time":1.442448505},
{"learn":[4.552940935],"iteration":262,"passed_time":0.5140937533,"remaining_time":1.440635347},
{"learn":[4.55004911],"iteration":263,"passed_time":0.5154048051,"remaining_time":1.436886123},
{"learn":[4.546696499],"iteration":264,"passed_time":0.5169502215,"remaining_time":1.433805331},
{"learn":[4.544522668],"iteration":265,"passed_time":0.5180868798,"remaining_time":1.429608157},
{"learn":[4.538695753],"iteration":266,"passed_time":0.5194653165,"remaining_time":1.426097667},
{"learn":[4.53416411],"iteration":267,"passed_time":0.5209874801,"remaining_time":1.422995655},
{"learn":[4.530741743],"iteration":268,"passed_time":0.5221664168,"remaining_time":1.418972679},
{"learn":[4.52611867],"iteration":269,"passed_time":0.5233028446,"remaining_time":1.414855839},
{"learn":[4.524277906],"iteration":270,"passed_time":0.5244164098,"remaining_time":1.410699493},
{"learn":[4.519270699],"iteration":271,"passed_time":0.5260022712,"remaining_time":1.407829608},
{"learn":[4.518645596],"iteration":272,"passed_time":0.5271042452,"remaining_time":1.403680536},
{"learn":[4.518156827],"iteration":273,"passed_time":0.5281587511,"remaining_time":1.399427932},
{"learn":[4.514140298],"iteration":274,"passed_time":0.529289288,"remaining_time":1.395399032},
{"learn":[4.510296321],"iteration":275,"passed_time":0.5304163084,"remaining_time":1.39138191},
{"learn":[4.504198156],"iteration":276,"passed_time":0.5316491451,"remaining_time":1.387661848},
{"learn":[4.501956177],"iteration":277,"passed_time":0.5327793814,"remaining_time":1.383693214},
{"learn":[4.498451015],"iteration":278,"passed_time":0.5338704852,"remaining_time":1.379643799},
{"learn":[4.494740533],"iteration":279,"passed_time":0.5350566553,"remaining_time":1.375859971},
{"learn":[4.490366351],"iteration":280,"passed_time":0.536171964,"remaining_time":1.371913317},
{"learn":[4.489544638],"iteration":281,"passed_time":0.5373853446,"remaining_time":1.368236445},
{"learn":[4.486267979],"iteration":282,"passed_time":0.5387047275,"remaining_time":1.364845546},
{"learn":[4.480754673],"iteration":283,"passed_time":0.5399008461,"remaining_time":1.361158471},
{"learn":[4.477328764],"iteration":284,"passed_time":0.5410174071,"remaining_time":1.357289284},
{"learn":[4.473037565],"iteration":285,"passed_time":0.5421333469,"remaining_time":1.353437796},
{"learn":[4.469931337],"iteration":286,"passed_time":0.5434257884,"remaining_time":1.350043858},
{"learn":[4.469591564],"iteration":287,"passed_time":0.5445539709,"remaining_time":1.346258428},
{"learn":[4.466096719],"iteration":288,"passed_time":0.5456736077,"remaining_time":1.342470363},
{"learn":[4.460002266],"iteration":289,"passed_time":0.5467961898,"remaining_time":1.338707913},
{"learn":[4.45555412],"iteration":290,"passed_time":0.5479341004,"remaining_time":1.335000953},
{"learn":[4.452712253],"iteration":291,"passed_time":0.5492281108,"remaining_time":1.331690077},
{"learn":[4.449225041],"iteration":292,"passed_time":0.550518504,"remaining_time":1.32838424},
{"learn":[4.447596446],"iteration":293,"passed_time":0.551696008,"remaining_time":1.324821026},
{"learn":[4.445562756],"iteration":294,"passed_time":0.5528665391,"remaining_time":1.321257322},
{"learn":[4.441961872],"iteration":295,"passed_time":0.5539703665,"remaining_time":1.317551142},
{"learn":[4.436055988],"iteration":296,"passed_time":0.5552008588,"remaining_time":1.314162302},
{"learn":[4.435486444],"iteration":297,"passed_time":0.5563711895,"remaining_time":1.310646225},
{"learn":[4.433587649],"iteration":298,"passed_time":0.5574820199,"remaining_time":1.307006341},
{"learn":[4.431374839],"iteration":299,"passed_time":0.5585780328,"remaining_time":1.303348743},
{"learn":[4.427346559],"iteration":300,"passed_time":0.5597064758,"remaining_time":1.299783477},
{"learn":[4.42439387],"iteration":301,"passed_time":0.5608592841,"remaining_time":1.296290663},
{"learn":[4.420599276],"iteration":302,"passed_time":0.5621537651,"remaining_time":1.293139189},
{"learn":[4.418809122],"iteration":303,"passed_time":0.5634127202,"remaining_time":1.289918596},
{"learn":[4.415002741],"iteration":304,"passed_time":0.5647821802,"remaining_time":1.286962673},
{"learn":[4.409047569],"iteration":305,"passed_time":0.5660463651,"remaining_time":1.283778357},
{"learn":[4.406194815],"iteration":306,"passed_time":0.5675823243,"remaining_time":1.281220035},
{"learn":[4.405775793],"iteration":307,"passed_time":0.5690475316,"remaining_time":1.278509389},
{"learn":[4.404385221],"iteration":308,"passed_time":0.5704541716,"remaining_time":1.275675834},
{"learn":[4.40057807],"iteration":309,"passed_time":0.5717983393,"remaining_time":1.272712433},
{"learn":[4.394694278],"iteration":310,"passed_time":0.5733009412,"remaining_time":1.270110445},
{"learn":[4.392253467],"iteration":311,"passed_time":0.574482142,"remaining_time":1.266806775},
{"learn":[4.387132134],"iteration":312,"passed_time":0.5757443732,"remaining_time":1.263694519},
{"learn":[4.381418147],"iteration":313,"passed_time":0.5770486482,"remaining_time":1.2606859},
{"learn":[4.377921678],"iteration":314,"passed_time":0.5784256565,"remaining_time":1.257846269},
{"learn":[4.373459732],"iteration":315,"passed_time":0.5803464045,"remaining_time":1.25619285},
{"learn":[4.370931069],"iteration":316,"passed_time":0.5818326664,"remaining_time":1.253601612},
{"learn":[4.36522851],"iteration":317,"passed_time":0.5830114729,"remaining_time":1.250357939},
{"learn":[4.362245844],"iteration":318,"passed_time":0.584131861,"remaining_time":1.247002499},
{"learn":[4.358715159],"iteration":319,"passed_time":0.5854585065,"remaining_time":1.244099326},
{"learn":[4.354941076],"iteration":320,"passed_time":0.5867185436,"remaining_time":1.241065081},
{"learn":[4.350267779],"iteration":321,"passed_time":0.5879012873,"remaining_time":1.237879108},
{"learn":[4.345570039],"iteration":322,"passed_time":0.5890543861,"remaining_time":1.234643404},
{"learn":[4.339706289],"iteration":323,"passed_time":0.5901959034,"remaining_time":1.231396391},
{"learn":[4.336322964],"iteration":324,"passed_time":0.5915591772,"remaining_time":1.228622906},
{"learn":[4.331251606],"iteration":325,"passed_time":0.5928005445,"remaining_time":1.225606034},
{"learn":[4.330841612],"iteration":326,"passed_time":0.5939296087,"remaining_time":1.222368889},
{"learn":[4.326721385],"iteration":327,"passed_time":0.5951001498,"remaining_time":1.219229575},
{"learn":[4.324368507],"iteration":328,"passed_time":0.5962916498,"remaining_time":1.216144976},
{"learn":[4.322070656],"iteration":329,"passed_time":0.5976880596,"remaining_time":1.213487878},
{"learn":[4.320849593],"iteration":330,"passed_time":0.5989367808,"remaining_time":1.210539898},
{"learn":[4.316562246],"iteration":331,"passed_time":0.6001391209,"remaining_time":1.207508834},
{"learn":[4.316256175],"iteration":332,"passed_time":0.6012183226,"remaining_time":1.204242106},
{"learn":[4.313250358],"iteration":333,"passed_time":0.6023430488,"remaining_time":1.201079253},
{"learn":[4.309995132],"iteration":334,"passed_time":0.6036008663,"remaining_time":1.198192764},
{"learn":[4.306481283],"iteration":335,"passed_time":0.6047826082,"remaining_time":1.195165631},
{"learn":[4.301294493],"iteration":336,"passed_time":0.6059322406,"remaining_time":1.192086277},
{"learn":[4.297046783],"iteration":337,"passed_time":0.6071029119,"remaining_time":1.189059549},
{"learn":[4.293844101],"iteration":338,"passed_time":0.6083029578,"remaining_time":1.186101047},
{"learn":[4.291924411],"iteration":339,"passed_time":0.6094772358,"remaining_time":1.18310287},
{"learn":[4.289649429],"iteration":340,"passed_time":0.6107318429,"remaining_time":1.180270629},
{"learn":[4.284662432],"iteration":341,"passed_time":0.6119136248,"remaining_time":1.1773075},
{"learn":[4.284140475],"iteration":342,"passed_time":0.6129722684,"remaining_time":1.174118893},
{"learn":[4.281138971],"iteration":343,"passed_time":0.6140679707,"remaining_time":1.17101334},
{"learn":[4.276879414],"iteration":344,"passed_time":0.6152887951,"remaining_time":1.168156988},
{"learn":[4.272496067],"iteration":345,"passed_time":0.616526601,"remaining_time":1.165342188},
{"learn":[4.270046442],"iteration":346,"passed_time":0.6176792088,"remaining_time":1.162376148},
{"learn":[4.268016808],"iteration":347,"passed_time":0.6188250341,"remaining_time":1.159407823},
{"learn":[4.264629952],"iteration":348,"passed_time":0.6199344919,"remaining_time":1.156382104},
{"learn":[4.261688019],"iteration":349,"passed_time":0.6210586571,"remaining_time":1.153394649},
{"learn":[4.259350413],"iteration":350,"passed_time":0.6223522664,"remaining_time":1.150731114},
{"learn":[4.255264543],"iteration":351,"passed_time":0.6235121378,"remaining_time":1.147829163},
{"learn":[4.251317671],"iteration":352,"passed_time":0.6246638339,"remaining_time":1.144922098},
{"learn":[4.247401086],"iteration":353,"passed_time":0.6257678116,"remaining_time":1.141937871},
{"learn":[4.24491493],"iteration":354,"passed_time":0.6268417936,"remaining_time":1.138909738},
{"learn":[4.243204608],"iteration":355,"passed_time":0.6281391008,"remaining_time":1.136296576},
{"learn":[4.241734529],"iteration":356,"passed_time":0.6292987617,"remaining_time":1.133442868},
{"learn":[4.237235774],"iteration":357,"passed_time":0.6304520609,"remaining_time":1.130587215},
{"learn":[4.236088664],"iteration":358,"passed_time":0.6315727495,"remaining_time":1.12768282},
{"learn":[4.230092869],"iteration":359,"passed_time":0.6327202779,"remaining_time":1.12483605},
{"learn":[4.226006305],"iteration":360,"passed_time":0.6339203229,"remaining_time":1.122091652},
{"learn":[4.222604956],"iteration":361,"passed_time":0.635095172,"remaining_time":1.11931138},
{"learn":[4.219967158],"iteration":362,"passed_time":0.6362167122,"remaining_time":1.116446407},
{"learn":[4.219085392],"iteration":363,"passed_time":0.6373092186,"remaining_time":1.113540283},
{"learn":[4.216817355],"iteration":364,"passed_time":0.6384190672,"remaining_time":1.110674268},
{"learn":[4.216513909],"iteration":365,"passed_time":0.6394985594,"remaining_time":1.107765264},
{"learn":[4.213040006],"iteration":366,"passed_time":0.6406881759,"remaining_time":1.105056173},
{"learn":[4.208955111],"iteration":367,"passed_time":0.6418370769,"remaining_time":1.102285415},
{"learn":[4.20724387],"iteration":368,"passed_time":0.6429061899,"remaining_time":1.099387008},
{"learn":[4.205074344],"iteration":369,"passed_time":0.6441290781,"remaining_time":1.096760322},
{"learn":[4.203914681],"iteration":370,"passed_time":0.6452415916,"remaining_time":1.093954073},
{"learn":[4.202153314],"iteration":371,"passed_time":0.6465546971,"remaining_time":1.091495564},
{"learn":[4.198948909],"iteration":372,"passed_time":0.6476904337,"remaining_time":1.088745045},
{"learn":[4.197869447],"iteration":373,"passed_time":0.6487709378,"remaining_time":1.085910714},
{"learn":[4.194442333],"iteration":374,"passed_time":0.6498798546,"remaining_time":1.083133091},
{"learn":[4.191743035],"iteration":375,"passed_time":0.6510303285,"remaining_time":1.080433311},
{"learn":[4.189099847],"iteration":376,"passed_time":0.6522697477,"remaining_time":1.077888734},
{"learn":[4.187334889],"iteration":377,"passed_time":0.6533831128,"remaining_time":1.075143641},
{"learn":[4.186895608],"iteration":378,"passed_time":0.6544688566,"remaining_time":1.0723619},
{"learn":[4.183350589],"iteration":379,"passed_time":0.6555907976,"remaining_time":1.069648143},
{"learn":[4.180652409],"iteration":380,"passed_time":0.6566886339,"remaining_time":1.066903581},
{"learn":[4.176663858],"iteration":381,"passed_time":0.6579918007,"remaining_time":1.064499824},
{"learn":[4.174989884],"iteration":382,"passed_time":0.6591615203,"remaining_time":1.061886836},
{"learn":[4.173678089],"iteration":383,"passed_time":0.6602756167,"remaining_time":1.059192135},
{"learn":[4.169628255],"iteration":384,"passed_time":0.6613987599,"remaining_time":1.056520097},
{"learn":[4.166778632],"iteration":385,"passed_time":0.6624755972,"remaining_time":1.053782427},
{"learn":[4.165265508],"iteration":386,"passed_time":0.6635664806,"remaining_time":1.051075588},
{"learn":[4.163755065],"iteration":387,"passed_time":0.6648012508,"remaining_time":1.048604035},
{"learn":[4.160299823],"iteration":388,"passed_time":0.6659393418,"remaining_time":1.045986987},
{"learn":[4.158766129],"iteration":389,"passed_time":0.6670667329,"remaining_time":1.043360787},
{"learn":[4.158389369],"iteration":390,"passed_time":0.6681203872,"remaining_time":1.040627406},
{"learn":[4.156461576],"iteration":391,"passed_time":0.6693472227,"remaining_time":1.038171203},
{"learn":[4.155814976],"iteration":392,"passed_time":0.6707691607,"remaining_time":1.036022597},
{"learn":[4.154362165],"iteration":393,"passed_time":0.6720587827,"remaining_time":1.033674168},
{"learn":[4.151177099],"iteration":394,"passed_time":0.6732041572,"remaining_time":1.031110165},
{"learn":[4.14999474],"iteration":395,"passed_time":0.6742969641,"remaining_time":1.028473147},
{"learn":[4.149533472],"iteration":396,"passed_time":0.6753844512,"remaining_time":1.025835829},
{"learn":[4.148160469],"iteration":397,"passed_time":0.6767309887,"remaining_time":1.023598129},
{"learn":[4.143964329],"iteration":398,"passed_time":0.6779936559,"remaining_time":1.021238564},
{"learn":[4.143719837],"iteration":399,"passed_time":0.6791026228,"remaining_time":1.018653934},
{"learn":[4.143381514],"iteration":400,"passed_time":0.6803107637,"remaining_time":1.016224807},
{"learn":[4.143184801],"iteration":401,"passed_time":0.6814770769,"remaining_time":1.013739532},
{"learn":[4.139892269],"iteration":402,"passed_time":0.6828839112,"remaining_time":1.011617109},
{"learn":[4.139119544],"iteration":403,"passed_time":0.6840778958,"remaining_time":1.009184223},
{"learn":[4.137219905],"iteration":404,"passed_time":0.6854037851,"remaining_time":1.00695124},
{"learn":[4.133153471],"iteration":405,"passed_time":0.6866362963,"remaining_time":1.004586108},
{"learn":[4.132568599],"iteration":406,"passed_time":0.6877442814,"remaining_time":1.002045108},
{"learn":[4.129058846],"iteration":407,"passed_time":0.6890049797,"remaining_time":0.9997327156},
{"learn":[4.127271215],"iteration":408,"passed_time":0.6901834555,"remaining_time":0.9973066558},
{"learn":[4.124806519],"iteration":409,"passed_time":0.691316437,"remaining_time":0.9948212142},
{"learn":[4.121459134],"iteration":410,"passed_time":0.6925256799,"remaining_time":0.9924516435},
{"learn":[4.118737497],"iteration":411,"passed_time":0.6936992066,"remaining_time":0.9900367317},
{"learn":[4.118378558],"iteration":412,"passed_time":0.6948698527,"remaining_time":0.9876237374},
{"learn":[4.118206618],"iteration":413,"passed_time":0.6958596137,"remaining_time":0.9849607092},
{"learn":[4.115783142],"iteration":414,"passed_time":0.6970142253,"remaining_time":0.9825381248},
{"learn":[4.113046144],"iteration":415,"passed_time":0.698189946,"remaining_time":0.9801512703},
{"learn":[4.108696983],"iteration":416,"passed_time":0.6995081558,"remaining_time":0.9779694361},
{"learn":[4.104882844],"iteration":417,"passed_time":0.700929943,"remaining_time":0.9759359493},
{"learn":[4.101100147],"iteration":418,"passed_time":0.702158091,"remaining_time":0.9736368755},
{"learn":[4.098235163],"iteration":419,"passed_time":0.7033297842,"remaining_time":0.9712649401},
{"learn":[4.095183161],"iteration":420,"passed_time":0.7045227269,"remaining_time":0.9689279308},
{"learn":[4.092801852],"iteration":421,"passed_time":0.7056525725,"remaining_time":0.9665099216},
{"learn":[4.087344856],"iteration":422,"passed_time":0.7069998214,"remaining_time":0.9643945554},
{"learn":[4.083053263],"iteration":423,"passed_time":0.7082297927,"remaining_time":0.962123492},
{"learn":[4.081450627],"iteration":424,"passed_time":0.7094012155,"remaining_time":0.9597781151},
{"learn":[4.080381959],"iteration":425,"passed_time":0.7104767204,"remaining_time":0.9573090082},
{"learn":[4.075940712],"iteration":426,"passed_time":0.7116059549,"remaining_time":0.9549185296},
{"learn":[4.068989292],"iteration":427,"passed_time":0.7129509848,"remaining_time":0.9528223441},
{"learn":[4.067409345],"iteration":428,"passed_time":0.7142586803,"remaining_time":0.9506799684},
{"learn":[4.067228069],"iteration":429,"passed_time":0.7155289163,"remaining_time":0.9484918193},
{"learn":[4.064963579],"iteration":430,"passed_time":0.7167557318,"remaining_time":0.9462506065},
{"learn":[4.061726578],"iteration":431,"passed_time":0.7179026692,"remaining_time":0.943909065},
{"learn":[4.059939524],"iteration":432,"passed_time":0.7191892856,"remaining_time":0.9417559467},
{"learn":[4.054230888],"iteration":433,"passed_time":0.7204238354,"remaining_time":0.939538919},
{"learn":[4.049424262],"iteration":434,"passed_time":0.7215846786,"remaining_time":0.9372306744},
{"learn":[4.045371843],"iteration":435,"passed_time":0.7227786331,"remaining_time":0.9349705254},
{"learn":[4.045187752],"iteration":436,"passed_time":0.7239389653,"remaining_time":0.9326719393},
{"learn":[4.042163672],"iteration":437,"passed_time":0.7256220871,"remaining_time":0.9310493447},
{"learn":[4.039784765],"iteration":438,"passed_time":0.727142462,"remaining_time":0.9292184993},
{"learn":[4.036889125],"iteration":439,"passed_time":0.7284032004,"remaining_time":0.9270586187},
{"learn":[4.033569203],"iteration":440,"passed_time":0.7296163405,"remaining_time":0.9248424815},
{"learn":[4.027882457],"iteration":441,"passed_time":0.7308139318,"remaining_time":0.9226112533},
{"learn":[4.025062911],"iteration":442,"passed_time":0.7321096151,"remaining_time":0.9205080262},
{"learn":[4.020889273],"iteration":443,"passed_time":0.7332634652,"remaining_time":0.9182308258},
{"learn":[4.020339092],"iteration":444,"passed_time":0.7343629045,"remaining_time":0.9158908134},
{"learn":[4.01726419],"iteration":445,"passed_time":0.7354841441,"remaining_time":0.9135834436},
{"learn":[4.016800401],"iteration":446,"passed_time":0.7365824413,"remaining_time":0.9112529978},
{"learn":[4.013425082],"iteration":447,"passed_time":0.738353311,"remaining_time":0.9097567582},
{"learn":[4.012928028],"iteration":448,"passed_time":0.7398580772,"remaining_time":0.9079327406},
{"learn":[4.010917145],"iteration":449,"passed_time":0.74128029,"remaining_time":0.9060092433},
{"learn":[4.006829036],"iteration":450,"passed_time":0.7425722062,"remaining_time":0.9039293597},
{"learn":[4.00380367],"iteration":451,"passed_time":0.7438509529,"remaining_time":0.901836996},
{"learn":[4.003501239],"iteration":452,"passed_time":0.7449861485,"remaining_time":0.8995748857},
{"learn":[4.001220068],"iteration":453,"passed_time":0.7460758296,"remaining_time":0.8972630021},
{"learn":[3.999146965],"iteration":454,"passed_time":0.7472049239,"remaining_time":0.8950037},
{"learn":[3.997632047],"iteration":455,"passed_time":0.7484204384,"remaining_time":0.8928524528},
{"learn":[3.996406432],"iteration":456,"passed_time":0.7495651817,"remaining_time":0.8906212115},
{"learn":[3.992991533],"iteration":457,"passed_time":0.7507425855,"remaining_time":0.8884333654},
{"learn":[3.988502654],"iteration":458,"passed_time":0.7519723865,"remaining_time":0.88631168},
{"learn":[3.984683095],"iteration":459,"passed_time":0.7530587415,"remaining_time":0.8840254792},
{"learn":[3.982412543],"iteration":460,"passed_time":0.7541808829,"remaining_time":0.8817863251},
{"learn":[3.980770464],"iteration":461,"passed_time":0.7553821209,"remaining_time":0.8796441148},
{"learn":[3.980284032],"iteration":462,"passed_time":0.7565318534,"remaining_time":0.8774462318},
{"learn":[3.975950496],"iteration":463,"passed_time":0.7576673195,"remaining_time":0.8752363863},
{"learn":[3.973823381],"iteration":464,"passed_time":0.7587804441,"remaining_time":0.8730054572},
{"learn":[3.968845921],"iteration":465,"passed_time":0.7599139566,"remaining_time":0.8708026884},
{"learn":[3.967933415],"iteration":466,"passed_time":0.760989241,"remaining_time":0.8685380417},
{"learn":[3.965419791],"iteration":467,"passed_time":0.7622635498,"remaining_time":0.866504719},
{"learn":[3.964511358],"iteration":468,"passed_time":0.7634531562,"remaining_time":0.8643787334},
{"learn":[3.963695014],"iteration":469,"passed_time":0.7645550801,"remaining_time":0.8621578563},
{"learn":[3.96345743],"iteration":470,"passed_time":0.7659523062,"remaining_time":0.860273397},
{"learn":[3.961738304],"iteration":471,"passed_time":0.7670657314,"remaining_time":0.85807353},
{"learn":[3.959215281],"iteration":472,"passed_time":0.768371854,"remaining_time":0.8560929536},
{"learn":[3.95512879],"iteration":473,"passed_time":0.7695174989,"remaining_time":0.8539371402},
{"learn":[3.952789839],"iteration":474,"passed_time":0.7706001671,"remaining_time":0.8517159741},
{"learn":[3.949183134],"iteration":475,"passed_time":0.7717370357,"remaining_time":0.8495592578},
{"learn":[3.947593245],"iteration":476,"passed_time":0.7728345714,"remaining_time":0.8473636915},
{"learn":[3.946239185],"iteration":477,"passed_time":0.7741090253,"remaining_time":0.845365923},
{"learn":[3.944537769],"iteration":478,"passed_time":0.7752647389,"remaining_time":0.8432420229},
{"learn":[3.942076397],"iteration":479,"passed_time":0.7763530475,"remaining_time":0.8410491348},
{"learn":[3.941937689],"iteration":480,"passed_time":0.7771842192,"remaining_time":0.8385833883},
{"learn":[3.937257321],"iteration":481,"passed_time":0.7782770161,"remaining_time":0.8364055899},
{"learn":[3.934323623],"iteration":482,"passed_time":0.779445293,"remaining_time":0.8343130776},
{"learn":[3.933628416],"iteration":483,"passed_time":0.7808184202,"remaining_time":0.8324427785},
{"learn":[3.930385379],"iteration":484,"passed_time":0.7819654778,"remaining_time":0.8303344764},
{"learn":[3.926242097],"iteration":485,"passed_time":0.7830723508,"remaining_time":0.8281876303},
{"learn":[3.924764551],"iteration":486,"passed_time":0.7841632241,"remaining_time":0.8260282012},
{"learn":[3.921634023],"iteration":487,"passed_time":0.7853074865,"remaining_time":0.8239291662},
{"learn":[3.916057162],"iteration":488,"passed_time":0.7866080285,"remaining_time":0.8219973467},
{"learn":[3.915004488],"iteration":489,"passed_time":0.7877327346,"remaining_time":0.8198850911},
{"learn":[3.911955981],"iteration":490,"passed_time":0.7888477327,"remaining_time":0.8177667941},
{"learn":[3.90935516],"iteration":491,"passed_time":0.7899486046,"remaining_time":0.8156379901},
{"learn":[3.907414007],"iteration":492,"passed_time":0.7910676702,"remaining_time":0.8135320665},
{"learn":[3.905025014],"iteration":493,"passed_time":0.7924891668,"remaining_time":0.8117399158},
{"learn":[3.90129815],"iteration":494,"passed_time":0.7936431171,"remaining_time":0.8096763114},
{"learn":[3.895956023],"iteration":495,"passed_time":0.7947708789,"remaining_time":0.8075897641},
{"learn":[3.895696589],"iteration":496,"passed_time":0.7958260861,"remaining_time":0.8054336445},
{"learn":[3.894062734],"iteration":497,"passed_time":0.796920486,"remaining_time":0.8033214538},
{"learn":[3.893887742],"iteration":498,"passed_time":0.7979974235,"remaining_time":0.80119581},
{"learn":[3.892319169],"iteration":499,"passed_time":0.7993110403,"remaining_time":0.7993110403},
{"learn":[3.890303301],"iteration":500,"passed_time":0.8004276314,"remaining_time":0.7972323115},
{"learn":[3.88776625],"iteration":501,"passed_time":0.8015565453,"remaining_time":0.7951696405},
{"learn":[3.883955331],"iteration":502,"passed_time":0.8026824536,"remaining_time":0.7931077126},
{"learn":[3.879862818],"iteration":503,"passed_time":0.8037976621,"remaining_time":0.7910389691},
{"learn":[3.878636955],"iteration":504,"passed_time":0.8051383388,"remaining_time":0.7891950054},
{"learn":[3.875845671],"iteration":505,"passed_time":0.8064564236,"remaining_time":0.7873309748},
{"learn":[3.872784497],"iteration":506,"passed_time":0.8076508991,"remaining_time":0.7853489019},
{"learn":[3.871629758],"iteration":507,"passed_time":0.8088065827,"remaining_time":0.7833323596},
{"learn":[3.870558781],"iteration":508,"passed_time":0.8098953521,"remaining_time":0.781254652},
{"learn":[3.866992911],"iteration":509,"passed_time":0.8112015549,"remaining_time":0.7793897292},
{"learn":[3.864717035],"iteration":510,"passed_time":0.8123194583,"remaining_time":0.7773468006},
{"learn":[3.863172355],"iteration":511,"passed_time":0.8134134575,"remaining_time":0.7752847017},
{"learn":[3.86053598],"iteration":512,"passed_time":0.8146279201,"remaining_time":0.773340735},
{"learn":[3.856921103],"iteration":513,"passed_time":0.8157685457,"remaining_time":0.7713297922},
{"learn":[3.856786887],"iteration":514,"passed_time":0.8169157435,"remaining_time":0.7693284187},
{"learn":[3.85412431],"iteration":515,"passed_time":0.8180349595,"remaining_time":0.7673041093},
{"learn":[3.853998107],"iteration":516,"passed_time":0.8188779831,"remaining_time":0.7650252724},
{"learn":[3.850888856],"iteration":517,"passed_time":0.8200397079,"remaining_time":0.7630485313},
{"learn":[3.847689003],"iteration":518,"passed_time":0.8211809346,"remaining_time":0.7610559336},
{"learn":[3.846386247],"iteration":519,"passed_time":0.8223266998,"remaining_time":0.7590707998},
{"learn":[3.842961367],"iteration":520,"passed_time":0.8236209203,"remaining_time":0.7572253759},
{"learn":[3.841478444],"iteration":521,"passed_time":0.8247507359,"remaining_time":0.7552315168},
{"learn":[3.839273249],"iteration":522,"passed_time":0.8258829459,"remaining_time":0.7532431457},
{"learn":[3.83749391],"iteration":523,"passed_time":0.82699581,"remaining_time":0.7512404687},
{"learn":[3.836377369],"iteration":524,"passed_time":0.8281409741,"remaining_time":0.7492704051},
{"learn":[3.835015558],"iteration":525,"passed_time":0.8294219501,"remaining_time":0.7474258637},
{"learn":[3.834803839],"iteration":526,"passed_time":0.830509377,"remaining_time":0.7454097445},
{"learn":[3.832936033],"iteration":527,"passed_time":0.831602234,"remaining_time":0.7434019971},
{"learn":[3.832813322],"iteration":528,"passed_time":0.8326330059,"remaining_time":0.7413424306},
{"learn":[3.830907787],"iteration":529,"passed_time":0.8338028558,"remaining_time":0.7394100796},
{"learn":[3.829332906],"iteration":530,"passed_time":0.835306124,"remaining_time":0.7377750888},
{"learn":[3.828155754],"iteration":531,"passed_time":0.8365099268,"remaining_time":0.7358771537},
{"learn":[3.82622883],"iteration":532,"passed_time":0.8376450523,"remaining_time":0.7339216499},
{"learn":[3.824484046],"iteration":533,"passed_time":0.8387687966,"remaining_time":0.7319592869},
{"learn":[3.821989383],"iteration":534,"passed_time":0.8398680154,"remaining_time":0.7299787424},
{"learn":[3.820381687],"iteration":535,"passed_time":0.8412856048,"remaining_time":0.7282770907},
{"learn":[3.817357932],"iteration":536,"passed_time":0.8424256493,"remaining_time":0.7263371986},
{"learn":[3.813916597],"iteration":537,"passed_time":0.8435594122,"remaining_time":0.7243948856},
{"learn":[3.812682094],"iteration":538,"passed_time":0.8446575691,"remaining_time":0.7224251194},
{"learn":[3.811048534],"iteration":539,"passed_time":0.8457675779,"remaining_time":0.7204686775},
{"learn":[3.808642875],"iteration":540,"passed_time":0.8469781132,"remaining_time":0.7186006543},
{"learn":[3.805820515],"iteration":541,"passed_time":0.8482437107,"remaining_time":0.7167815858},
{"learn":[3.802507558],"iteration":542,"passed_time":0.8494102444,"remaining_time":0.7148811817},
{"learn":[3.801308068],"iteration":543,"passed_time":0.8504972004,"remaining_time":0.712916771},
{"learn":[3.797612278],"iteration":544,"passed_time":0.851621626,"remaining_time":0.7109868621},
{"learn":[3.795289101],"iteration":545,"passed_time":0.8530413694,"remaining_time":0.709305461},
{"learn":[3.792462095],"iteration":546,"passed_time":0.8542654097,"remaining_time":0.7074629444},
{"learn":[3.792311665],"iteration":547,"passed_time":0.85531687,"remaining_time":0.705480338},
{"learn":[3.790577279],"iteration":548,"passed_time":0.8564396225,"remaining_time":0.7035596898},
{"learn":[3.789601224],"iteration":549,"passed_time":0.8575324594,"remaining_time":0.7016174668},
{"learn":[3.788433049],"iteration":550,"passed_time":0.8586480186,"remaining_time":0.6996968427},
{"learn":[3.78699353],"iteration":551,"passed_time":0.8599537104,"remaining_time":0.6979334461},
{"learn":[3.785292353],"iteration":552,"passed_time":0.8610692996,"remaining_time":0.6960180414},
{"learn":[3.783470876],"iteration":553,"passed_time":0.8628655516,"remaining_time":0.6946534946},
{"learn":[3.781334898],"iteration":554,"passed_time":0.8641750702,"remaining_time":0.6928971283},
{"learn":[3.777812441],"iteration":555,"passed_time":0.8657307156,"remaining_time":0.6913389168},
{"learn":[3.775864292],"iteration":556,"passed_time":0.8670760767,"remaining_time":0.6896134686},
{"learn":[3.774653751],"iteration":557,"passed_time":0.8682625073,"remaining_time":0.6877634915},
{"learn":[3.774512993],"iteration":558,"passed_time":0.8693321513,"remaining_time":0.6858237544},
{"learn":[3.772748322],"iteration":559,"passed_time":0.8704444444,"remaining_time":0.6839206349},
{"learn":[3.770309743],"iteration":560,"passed_time":0.8719366063,"remaining_time":0.6823175939},
{"learn":[3.770154144],"iteration":561,"passed_time":0.8730405138,"remaining_time":0.6804123577},
{"learn":[3.766833263],"iteration":562,"passed_time":0.8741708303,"remaining_time":0.6785304669},
{"learn":[3.764794957],"iteration":563,"passed_time":0.8753462104,"remaining_time":0.6766860776},
{"learn":[3.762769211],"iteration":564,"passed_time":0.8764968947,"remaining_time":0.6748250428},
{"learn":[3.761325264],"iteration":565,"passed_time":0.8777871579,"remaining_time":0.6730735451},
{"learn":[3.76089942],"iteration":566,"passed_time":0.8789010339,"remaining_time":0.671188973},
{"learn":[3.757521874],"iteration":567,"passed_time":0.8800085682,"remaining_time":0.6693022913},
{"learn":[3.755697695],"iteration":568,"passed_time":0.881122334,"remaining_time":0.6674230684},
{"learn":[3.75500148],"iteration":569,"passed_time":0.8822018462,"remaining_time":0.665520691},
{"learn":[3.754594087],"iteration":570,"passed_time":0.8832827812,"remaining_time":0.6636222647},
{"learn":[3.751086555],"iteration":571,"passed_time":0.8845730744,"remaining_time":0.6618833494},
{"learn":[3.746184449],"iteration":572,"passed_time":0.8856949252,"remaining_time":0.6600204766},
{"learn":[3.744167544],"iteration":573,"passed_time":0.8868168061,"remaining_time":0.658160208},
{"learn":[3.742362378],"iteration":574,"passed_time":0.8878978011,"remaining_time":0.6562722878},
{"learn":[3.741173653],"iteration":575,"passed_time":0.8890189707,"remaining_time":0.6544167423},
{"learn":[3.739588265],"iteration":576,"passed_time":0.890361641,"remaining_time":0.6527261251},
{"learn":[3.735501509],"iteration":577,"passed_time":0.8915073862,"remaining_time":0.6508929359},
{"learn":[3.732980064],"iteration":578,"passed_time":0.8926139386,"remaining_time":0.6490336238},
{"learn":[3.730319962],"iteration":579,"passed_time":0.8937208317,"remaining_time":0.647177154},
{"learn":[3.729449548],"iteration":580,"passed_time":0.8947977491,"remaining_time":0.645301647},
{"learn":[3.72881929],"iteration":581,"passed_time":0.8960032351,"remaining_time":0.6435212238},
{"learn":[3.728614494],"iteration":582,"passed_time":0.8971810196,"remaining_time":0.6417229592},
{"learn":[3.727671672],"iteration":583,"passed_time":0.8982831439,"remaining_time":0.6398729244},
{"learn":[3.727480454],"iteration":584,"passed_time":0.8993085658,"remaining_time":0.6379710339},
{"learn":[3.722801057],"iteration":585,"passed_time":0.900432771,"remaining_time":0.6361419235},
{"learn":[3.719153145],"iteration":586,"passed_time":0.9015784961,"remaining_time":0.6343303558},
{"learn":[3.716436698],"iteration":587,"passed_time":0.9027840922,"remaining_time":0.6325630034},
{"learn":[3.71591304],"iteration":588,"passed_time":0.9039944071,"remaining_time":0.6308008511},
{"learn":[3.714079857],"iteration":589,"passed_time":0.9051051373,"remaining_time":0.6289713666},
{"learn":[3.712472218],"iteration":590,"passed_time":0.9062079628,"remaining_time":0.627138844},
{"learn":[3.708753824],"iteration":591,"passed_time":0.9074272046,"remaining_time":0.6253890194},
{"learn":[3.704710758],"iteration":592,"passed_time":0.9088196272,"remaining_time":0.6237598453},
{"learn":[3.703443858],"iteration":593,"passed_time":0.909929055,"remaining_time":0.621938041},
{"learn":[3.702134237],"iteration":594,"passed_time":0.9110289751,"remaining_time":0.6201121595},
{"learn":[3.702043828],"iteration":595,"passed_time":0.9120912354,"remaining_time":0.6182631864},
{"learn":[3.698709588],"iteration":596,"passed_time":0.9131954435,"remaining_time":0.6164451654},
{"learn":[3.69603077],"iteration":597,"passed_time":0.9144741252,"remaining_time":0.6147468199},
{"learn":[3.692521843],"iteration":598,"passed_time":0.9156285364,"remaining_time":0.612966683},
{"learn":[3.690674126],"iteration":599,"passed_time":0.9167378439,"remaining_time":0.6111585626},
{"learn":[3.687713977],"iteration":600,"passed_time":0.9180255524,"remaining_time":0.609471207},
{"learn":[3.685420009],"iteration":601,"passed_time":0.9192207392,"remaining_time":0.6077240103},
{"learn":[3.684553108],"iteration":602,"passed_time":0.9208065706,"remaining_time":0.6062358351},
{"learn":[3.679917082],"iteration":603,"passed_time":0.9220379546,"remaining_time":0.6045149504},
{"learn":[3.678348461],"iteration":604,"passed_time":0.9231422729,"remaining_time":0.6027127236},
{"learn":[3.677115497],"iteration":605,"passed_time":0.9242348093,"remaining_time":0.6009051401},
{"learn":[3.673953249],"iteration":606,"passed_time":0.9253677106,"remaining_time":0.5991260466},
{"learn":[3.669320375],"iteration":607,"passed_time":0.9267063733,"remaining_time":0.5974817407},
{"learn":[3.668655278],"iteration":608,"passed_time":0.9278444141,"remaining_time":0.5957096321},
{"learn":[3.667285803],"iteration":609,"passed_time":0.92895821,"remaining_time":0.5939241015},
{"learn":[3.66516807],"iteration":610,"passed_time":0.9300509167,"remaining_time":0.5921273431},
{"learn":[3.661825741],"iteration":611,"passed_time":0.9312952347,"remaining_time":0.590429005},
{"learn":[3.6566609],"iteration":612,"passed_time":0.9328563803,"remaining_time":0.5889321683},
{"learn":[3.654375057],"iteration":613,"passed_time":0.9342209113,"remaining_time":0.5873115175},
{"learn":[3.653208104],"iteration":614,"passed_time":0.9356912937,"remaining_time":0.5857579643},
{"learn":[3.651747007],"iteration":615,"passed_time":0.9377976111,"remaining_time":0.5846011082},
{"learn":[3.648806814],"iteration":616,"passed_time":0.9406312269,"remaining_time":0.5838926416},
{"learn":[3.647727273],"iteration":617,"passed_time":0.9418478434,"remaining_time":0.5821777932},
{"learn":[3.646068375],"iteration":618,"passed_time":0.9433980533,"remaining_time":0.5806698842},
{"learn":[3.644089319],"iteration":619,"passed_time":0.9455952587,"remaining_time":0.5795583844},
{"learn":[3.643108188],"iteration":620,"passed_time":0.9468654847,"remaining_time":0.5778776469},
{"learn":[3.640997902],"iteration":621,"passed_time":0.9480698686,"remaining_time":0.576158216},
{"learn":[3.637879623],"iteration":622,"passed_time":0.9506158008,"remaining_time":0.5752522583},
{"learn":[3.635547658],"iteration":623,"passed_time":0.9526757616,"remaining_time":0.5740482153},
{"learn":[3.634657529],"iteration":624,"passed_time":0.9543306362,"remaining_time":0.5725983817},
{"learn":[3.632707104],"iteration":625,"passed_time":0.9555621705,"remaining_time":0.5708949709},
{"learn":[3.631672793],"iteration":626,"passed_time":0.9568918116,"remaining_time":0.5692514286},
{"learn":[3.629537523],"iteration":627,"passed_time":0.9590227337,"remaining_time":0.5680835301},
{"learn":[3.628364521],"iteration":628,"passed_time":0.9604004892,"remaining_time":0.566468333},
{"learn":[3.626846067],"iteration":629,"passed_time":0.9617807192,"remaining_time":0.564855343},
{"learn":[3.625465875],"iteration":630,"passed_time":0.9630839564,"remaining_time":0.5631980664},
{"learn":[3.623294616],"iteration":631,"passed_time":0.9645898095,"remaining_time":0.5616598891},
{"learn":[3.622095012],"iteration":632,"passed_time":0.9660739723,"remaining_time":0.5601092383},
{"learn":[3.620608061],"iteration":633,"passed_time":0.9674401964,"remaining_time":0.5584907128},
{"learn":[3.618974266],"iteration":634,"passed_time":0.9686536471,"remaining_time":0.5567851672},
{"learn":[3.616374123],"iteration":635,"passed_time":0.9708419262,"remaining_time":0.5556390899},
{"learn":[3.615949781],"iteration":636,"passed_time":0.9723159903,"remaining_time":0.5540827386},
{"learn":[3.615275067],"iteration":637,"passed_time":0.9737248383,"remaining_time":0.5524896418},
{"learn":[3.612936397],"iteration":638,"passed_time":0.9749926799,"remaining_time":0.5508174608},
{"learn":[3.61209535],"iteration":639,"passed_time":0.9785251264,"remaining_time":0.5504203836},
{"learn":[3.610270635],"iteration":640,"passed_time":0.9798560654,"remaining_time":0.5487805421},
{"learn":[3.608172708],"iteration":641,"passed_time":0.9812524208,"remaining_time":0.5471781412},
{"learn":[3.605827682],"iteration":642,"passed_time":0.9830348711,"remaining_time":0.5457907449},
{"learn":[3.605151478],"iteration":643,"passed_time":0.9842734685,"remaining_time":0.5441014826},
{"learn":[3.604348336],"iteration":644,"passed_time":0.9854955856,"remaining_time":0.5424045471},
{"learn":[3.604093713],"iteration":645,"passed_time":0.9867207881,"remaining_time":0.5407107724},
{"learn":[3.601511217],"iteration":646,"passed_time":0.9882235354,"remaining_time":0.5391698732},
{"learn":[3.60113423],"iteration":647,"passed_time":0.9896143751,"remaining_time":0.5375683025},
{"learn":[3.600719842],"iteration":648,"passed_time":0.9909569653,"remaining_time":0.5359412863},
{"learn":[3.599304015],"iteration":649,"passed_time":0.9921138311,"remaining_time":0.5342151398},
{"learn":[3.59657587],"iteration":650,"passed_time":0.9932908142,"remaining_time":0.5325015271},
{"learn":[3.594080726],"iteration":651,"passed_time":0.9947623432,"remaining_time":0.5309467722},
{"learn":[3.589729523],"iteration":652,"passed_time":0.9960447318,"remaining_time":0.5292917641},
{"learn":[3.588689947],"iteration":653,"passed_time":0.9973118421,"remaining_time":0.5276298125},
{"learn":[3.586137673],"iteration":654,"passed_time":0.9985993401,"remaining_time":0.5259798051},
{"learn":[3.585211577],"iteration":655,"passed_time":0.9999165533,"remaining_time":0.5243464853},
{"learn":[3.581297412],"iteration":656,"passed_time":1.001482944,"remaining_time":0.522844216},
{"learn":[3.578127196],"iteration":657,"passed_time":1.002675546,"remaining_time":0.5211474725},
{"learn":[3.575511401],"iteration":658,"passed_time":1.003849023,"remaining_time":0.5194423624},
{"learn":[3.573527489],"iteration":659,"passed_time":1.006450328,"remaining_time":0.5184744113},
{"learn":[3.572909917],"iteration":660,"passed_time":1.008142106,"remaining_time":0.5170350588},
{"learn":[3.572183728],"iteration":661,"passed_time":1.009739909,"remaining_time":0.5155469625},
{"learn":[3.570950807],"iteration":662,"passed_time":1.011166981,"remaining_time":0.5139717533},
{"learn":[3.567046957],"iteration":663,"passed_time":1.012686389,"remaining_time":0.5124437148},
{"learn":[3.56516645],"iteration":664,"passed_time":1.014138502,"remaining_time":0.5108818018},
{"learn":[3.563062089],"iteration":665,"passed_time":1.015509866,"remaining_time":0.5092797225},
{"learn":[3.557306652],"iteration":666,"passed_time":1.016757279,"remaining_time":0.5076164529},
{"learn":[3.556961746],"iteration":667,"passed_time":1.017961072,"remaining_time":0.5059327485},
{"learn":[3.556339012],"iteration":668,"passed_time":1.019584403,"remaining_time":0.504458053},
{"learn":[3.554998055],"iteration":669,"passed_time":1.021100585,"remaining_time":0.5029301391},
{"learn":[3.553736687],"iteration":670,"passed_time":1.022487939,"remaining_time":0.5013390936},
{"learn":[3.549659311],"iteration":671,"passed_time":1.023725705,"remaining_time":0.4996756415},
{"learn":[3.547852912],"iteration":672,"passed_time":1.025019775,"remaining_time":0.4980408118},
{"learn":[3.545676459],"iteration":673,"passed_time":1.026394344,"remaining_time":0.4964459291},
{"learn":[3.54508172],"iteration":674,"passed_time":1.027631489,"remaining_time":0.4947855317},
{"learn":[3.544655462],"iteration":675,"passed_time":1.02916043,"remaining_time":0.4932662416},
{"learn":[3.54305655],"iteration":676,"passed_time":1.030625217,"remaining_time":0.491716315},
{"learn":[3.540691251],"iteration":677,"passed_time":1.032045467,"remaining_time":0.4901454871},
{"learn":[3.540189819],"iteration":678,"passed_time":1.033329729,"remaining_time":0.4885108143},
{"learn":[3.539566846],"iteration":679,"passed_time":1.034578144,"remaining_time":0.4868603032},
{"learn":[3.538232098],"iteration":680,"passed_time":1.035881301,"remaining_time":0.4852366155},
{"learn":[3.53535619],"iteration":681,"passed_time":1.037384389,"remaining_time":0.4837070906},
{"learn":[3.533804167],"iteration":682,"passed_time":1.038697324,"remaining_time":0.4820893878},
{"learn":[3.52947244],"iteration":683,"passed_time":1.039976497,"remaining_time":0.4804569782},
{"learn":[3.525668932],"iteration":684,"passed_time":1.0412234,"remaining_time":0.4788107605},
{"learn":[3.525192947],"iteration":685,"passed_time":1.042641069,"remaining_time":0.4772438714},
{"learn":[3.523988929],"iteration":686,"passed_time":1.044097716,"remaining_time":0.4756951748},
{"learn":[3.522008896],"iteration":687,"passed_time":1.045422122,"remaining_time":0.4740867765},
{"learn":[3.520189312],"iteration":688,"passed_time":1.046788747,"remaining_time":0.4724982589},
{"learn":[3.519149689],"iteration":689,"passed_time":1.048081124,"remaining_time":0.4708770269},
{"learn":[3.516561289],"iteration":690,"passed_time":1.049598319,"remaining_time":0.4693572799},
{"learn":[3.515434768],"iteration":691,"passed_time":1.050890135,"remaining_time":0.4677372275},
{"learn":[3.514889918],"iteration":692,"passed_time":1.052120767,"remaining_time":0.4660910181},
{"learn":[3.510469496],"iteration":693,"passed_time":1.05341629,"remaining_time":0.4644746178},
{"learn":[3.510380123],"iteration":694,"passed_time":1.054695869,"remaining_time":0.462852144},
{"learn":[3.509195196],"iteration":695,"passed_time":1.05662108,"remaining_time":0.4615126557},
{"learn":[3.507432219],"iteration":696,"passed_time":1.057792653,"remaining_time":0.459843865},
{"learn":[3.504657545],"iteration":697,"passed_time":1.058988962,"remaining_time":0.4581872013},
{"learn":[3.504578504],"iteration":698,"passed_time":1.06004457,"remaining_time":0.4564712669},
{"learn":[3.499947735],"iteration":699,"passed_time":1.06183746,"remaining_time":0.4550731971},
{"learn":[3.496515715],"iteration":700,"passed_time":1.063181643,"remaining_time":0.4534826124},
{"learn":[3.494615439],"iteration":701,"passed_time":1.064514315,"remaining_time":0.4518878431},
{"learn":[3.494396741],"iteration":702,"passed_time":1.065677573,"remaining_time":0.4502222462},
{"learn":[3.493847156],"iteration":703,"passed_time":1.066942409,"remaining_time":0.4486007857},
{"learn":[3.492039867],"iteration":704,"passed_time":1.068410047,"remaining_time":0.4470651968},
{"learn":[3.491490038],"iteration":705,"passed_time":1.069644096,"remaining_time":0.4454325273},
{"learn":[3.490502199],"iteration":706,"passed_time":1.070911231,"remaining_time":0.4438146967},
{"learn":[3.485185577],"iteration":707,"passed_time":1.072197186,"remaining_time":0.4422056191},
{"learn":[3.484016356],"iteration":708,"passed_time":1.07370055,"remaining_time":0.4406866855},
{"learn":[3.483105456],"iteration":709,"passed_time":1.075844096,"remaining_time":0.4394292786},
{"learn":[3.482026652],"iteration":710,"passed_time":1.077087512,"remaining_time":0.4378035035},
{"learn":[3.481558176],"iteration":711,"passed_time":1.078231294,"remaining_time":0.4361385008},
{"learn":[3.480747935],"iteration":712,"passed_time":1.079659838,"remaining_time":0.4345895843},
{"learn":[3.479641186],"iteration":713,"passed_time":1.081056063,"remaining_time":0.4330280587},
{"learn":[3.478507636],"iteration":714,"passed_time":1.082945467,"remaining_time":0.4316635778},
{"learn":[3.47757714],"iteration":715,"passed_time":1.085087645,"remaining_time":0.4303978927},
{"learn":[3.476168714],"iteration":716,"passed_time":1.086703853,"remaining_time":0.4289221624},
{"learn":[3.475051842],"iteration":717,"passed_time":1.088067081,"remaining_time":0.427346681},
{"learn":[3.472274587],"iteration":718,"passed_time":1.089285331,"remaining_time":0.4257151293},
{"learn":[3.469058759],"iteration":719,"passed_time":1.090466452,"remaining_time":0.4240702868},
{"learn":[3.466602297],"iteration":720,"passed_time":1.091648053,"remaining_time":0.4224269166},
{"learn":[3.465142062],"iteration":721,"passed_time":1.092793318,"remaining_time":0.4207708342},
{"learn":[3.464077023],"iteration":722,"passed_time":1.093886966,"remaining_time":0.4190963895},
{"learn":[3.463428582],"iteration":723,"passed_time":1.094979853,"remaining_time":0.4174232589},
{"learn":[3.460254358],"iteration":724,"passed_time":1.096103858,"remaining_time":0.4157635323},
{"learn":[3.458239195],"iteration":725,"passed_time":1.097526502,"remaining_time":0.4142179912},
{"learn":[3.456792697],"iteration":726,"passed_time":1.09875984,"remaining_time":0.4126017005},
{"learn":[3.45365279],"iteration":727,"passed_time":1.099949256,"remaining_time":0.4109700516},
{"learn":[3.452839253],"iteration":728,"passed_time":1.101089781,"remaining_time":0.4093214413},
{"learn":[3.451704729],"iteration":729,"passed_time":1.102296605,"remaining_time":0.4076987441},
{"learn":[3.450754099],"iteration":730,"passed_time":1.103560388,"remaining_time":0.4060981456},
{"learn":[3.447733579],"iteration":731,"passed_time":1.104687228,"remaining_time":0.4044483295},
{"learn":[3.447593067],"iteration":732,"passed_time":1.10575004,"remaining_time":0.4027766175},
{"learn":[3.444056273],"iteration":733,"passed_time":1.106856021,"remaining_time":0.4011222093},
{"learn":[3.441770983],"iteration":734,"passed_time":1.107926366,"remaining_time":0.399456445},
{"learn":[3.440342469],"iteration":735,"passed_time":1.109183618,"remaining_time":0.3978593413},
{"learn":[3.437742226],"iteration":736,"passed_time":1.110335966,"remaining_time":0.3962257245},
{"learn":[3.436218003],"iteration":737,"passed_time":1.111465942,"remaining_time":0.3945854698},
{"learn":[3.43529309],"iteration":738,"passed_time":1.11258101,"remaining_time":0.3929413309},
{"learn":[3.432916917],"iteration":739,"passed_time":1.113699043,"remaining_time":0.3912996639},
{"learn":[3.431824168],"iteration":740,"passed_time":1.114945436,"remaining_time":0.3897042751},
{"learn":[3.431388753],"iteration":741,"passed_time":1.116060113,"remaining_time":0.3880640285},
{"learn":[3.429861925],"iteration":742,"passed_time":1.117191942,"remaining_time":0.3864311295},
{"learn":[3.42907959],"iteration":743,"passed_time":1.118256146,"remaining_time":0.3847763084},
{"learn":[3.426385522],"iteration":744,"passed_time":1.119377646,"remaining_time":0.3831426844},
{"learn":[3.425926845],"iteration":745,"passed_time":1.120557074,"remaining_time":0.3815301566},
{"learn":[3.423259947],"iteration":746,"passed_time":1.121730901,"remaining_time":0.3799168916},
{"learn":[3.422273428],"iteration":747,"passed_time":1.122917412,"remaining_time":0.3783090746},
{"learn":[3.420279373],"iteration":748,"passed_time":1.124050103,"remaining_time":0.3766843469},
{"learn":[3.417012272],"iteration":749,"passed_time":1.12536941,"remaining_time":0.3751231366},
{"learn":[3.416103796],"iteration":750,"passed_time":1.126525344,"remaining_time":0.3735084029},
{"learn":[3.413099015],"iteration":751,"passed_time":1.127859639,"remaining_time":0.3719537109},
{"learn":[3.410011822],"iteration":752,"passed_time":1.129012317,"remaining_time":0.3703400298},
{"learn":[3.407893169],"iteration":753,"passed_time":1.130145119,"remaining_time":0.3687210864},
{"learn":[3.405840778],"iteration":754,"passed_time":1.131287427,"remaining_time":0.3671065162},
{"learn":[3.40441704],"iteration":755,"passed_time":1.132383009,"remaining_time":0.3654781142},
{"learn":[3.402127564],"iteration":756,"passed_time":1.133595618,"remaining_time":0.3638886858},
{"learn":[3.401266512],"iteration":757,"passed_time":1.134740081,"remaining_time":0.3622784954},
{"learn":[3.399504029],"iteration":758,"passed_time":1.135872501,"remaining_time":0.3606657085},
{"learn":[3.398012069],"iteration":759,"passed_time":1.136975367,"remaining_time":0.3590448527},
{"learn":[3.39599949],"iteration":760,"passed_time":1.138451555,"remaining_time":0.3575426039},
{"learn":[3.394049239],"iteration":761,"passed_time":1.139805345,"remaining_time":0.3560021945},
{"learn":[3.393565416],"iteration":762,"passed_time":1.140889627,"remaining_time":0.3543785603},
{"learn":[3.393474985],"iteration":763,"passed_time":1.141914798,"remaining_time":0.352738079},
{"learn":[3.39253699],"iteration":764,"passed_time":1.142989782,"remaining_time":0.3511145082},
{"learn":[3.391252275],"iteration":765,"passed_time":1.144086566,"remaining_time":0.3494990294},
{"learn":[3.390910645],"iteration":766,"passed_time":1.145270823,"remaining_time":0.3479114756},
{"learn":[3.388398673],"iteration":767,"passed_time":1.146457644,"remaining_time":0.3463257468},
{"learn":[3.386923689],"iteration":768,"passed_time":1.147597228,"remaining_time":0.3447268657},
{"learn":[3.386033985],"iteration":769,"passed_time":1.14869243,"remaining_time":0.3431159205},
{"learn":[3.385606322],"iteration":770,"passed_time":1.149767464,"remaining_time":0.3415003231},
{"learn":[3.384036018],"iteration":771,"passed_time":1.150889845,"remaining_time":0.3399001098},
{"learn":[3.381911117],"iteration":772,"passed_time":1.152217958,"remaining_time":0.3383615479},
{"learn":[3.37985535],"iteration":773,"passed_time":1.153362141,"remaining_time":0.336769824},
{"learn":[3.377901957],"iteration":774,"passed_time":1.154479323,"remaining_time":0.3351714163},
{"learn":[3.377507703],"iteration":775,"passed_time":1.155592157,"remaining_time":0.3335729937},
{"learn":[3.37571583],"iteration":776,"passed_time":1.156677861,"remaining_time":0.3319680346},
{"learn":[3.373205914],"iteration":777,"passed_time":1.157927739,"remaining_time":0.3304112571},
{"learn":[3.371467658],"iteration":778,"passed_time":1.159059208,"remaining_time":0.3288216751},
{"learn":[3.369265139],"iteration":779,"passed_time":1.160156573,"remaining_time":0.3272236488},
{"learn":[3.366576698],"iteration":780,"passed_time":1.16126542,"remaining_time":0.3256301241},
{"learn":[3.365227951],"iteration":781,"passed_time":1.162404563,"remaining_time":0.3240462847},
{"learn":[3.3647326],"iteration":782,"passed_time":1.163528066,"remaining_time":0.322459247},
{"learn":[3.363473917],"iteration":783,"passed_time":1.164741577,"remaining_time":0.3208981896},
{"learn":[3.36251741],"iteration":784,"passed_time":1.165905827,"remaining_time":0.3193245258},
{"learn":[3.362421323],"iteration":785,"passed_time":1.166959651,"remaining_time":0.3177218389},
{"learn":[3.360517837],"iteration":786,"passed_time":1.168077505,"remaining_time":0.3161378761},
{"learn":[3.360393541],"iteration":787,"passed_time":1.169141308,"remaining_time":0.3145405549},
{"learn":[3.35923277],"iteration":788,"passed_time":1.170417646,"remaining_time":0.3130014236},
{"learn":[3.355682508],"iteration":789,"passed_time":1.171528997,"remaining_time":0.3114191004},
{"learn":[3.35333884],"iteration":790,"passed_time":1.172661337,"remaining_time":0.3098435138},
{"learn":[3.352830574],"iteration":791,"passed_time":1.173736161,"remaining_time":0.3082539412},
{"learn":[3.352745869],"iteration":792,"passed_time":1.174763867,"remaining_time":0.3066533675},
{"learn":[3.351769094],"iteration":793,"passed_time":1.176065882,"remaining_time":0.3051254051},
{"learn":[3.350789408],"iteration":794,"passed_time":1.177206317,"remaining_time":0.3035563459},
{"learn":[3.34952514],"iteration":795,"passed_time":1.178304474,"remaining_time":0.3019775285},
{"learn":[3.346319101],"iteration":796,"passed_time":1.179432336,"remaining_time":0.3004074833},
{"learn":[3.344694945],"iteration":797,"passed_time":1.180602126,"remaining_time":0.2988491596},
{"learn":[3.343269538],"iteration":798,"passed_time":1.181783877,"remaining_time":0.2972948177},
{"learn":[3.341062116],"iteration":799,"passed_time":1.182930584,"remaining_time":0.2957326461},
{"learn":[3.340599002],"iteration":800,"passed_time":1.184061883,"remaining_time":0.2941676837},
{"learn":[3.33778943],"iteration":801,"passed_time":1.185209842,"remaining_time":0.292607916},
{"learn":[3.335915572],"iteration":802,"passed_time":1.186410499,"remaining_time":0.2910621024},
{"learn":[3.335858023],"iteration":803,"passed_time":1.187498998,"remaining_time":0.2894898054},
{"learn":[3.334340558],"iteration":804,"passed_time":1.188664089,"remaining_time":0.2879372637},
{"learn":[3.331812164],"iteration":805,"passed_time":1.189785068,"remaining_time":0.286375066},
{"learn":[3.330804171],"iteration":806,"passed_time":1.190895197,"remaining_time":0.2848113668},
{"learn":[3.330102978],"iteration":807,"passed_time":1.19199139,"remaining_time":0.2832454789},
{"learn":[3.328237401],"iteration":808,"passed_time":1.193141654,"remaining_time":0.2816935177},
{"learn":[3.326905948],"iteration":809,"passed_time":1.19433627,"remaining_time":0.2801529522},
{"learn":[3.326139234],"iteration":810,"passed_time":1.195456988,"remaining_time":0.2785960183},
{"learn":[3.324806786],"iteration":811,"passed_time":1.196596732,"remaining_time":0.2770445637},
{"learn":[3.324335755],"iteration":812,"passed_time":1.197680342,"remaining_time":0.2754812104},
{"learn":[3.322690679],"iteration":813,"passed_time":1.198805579,"remaining_time":0.2739285476},
{"learn":[3.321168353],"iteration":814,"passed_time":1.199965721,"remaining_time":0.2723848569},
{"learn":[3.320492108],"iteration":815,"passed_time":1.201115263,"remaining_time":0.2708397162},
{"learn":[3.31989192],"iteration":816,"passed_time":1.202220944,"remaining_time":0.2692857194},
{"learn":[3.318991578],"iteration":817,"passed_time":1.203334309,"remaining_time":0.2677345284},
{"learn":[3.318329971],"iteration":818,"passed_time":1.204432526,"remaining_time":0.2661810589},
{"learn":[3.317443552],"iteration":819,"passed_time":1.205532446,"remaining_time":0.2646290735},
{"learn":[3.314516816],"iteration":820,"passed_time":1.206679564,"remaining_time":0.2630884798},
{"learn":[3.312502008],"iteration":821,"passed_time":1.207878979,"remaining_time":0.2615601681},
{"learn":[3.312392405],"iteration":822,"passed_time":1.208795729,"remaining_time":0.2599718639},
{"learn":[3.311378362],"iteration":823,"passed_time":1.209924072,"remaining_time":0.2584303843},
{"learn":[3.311189513],"iteration":824,"passed_time":1.210987154,"remaining_time":0.2568760629},
{"learn":[3.308680417],"iteration":825,"passed_time":1.212339101,"remaining_time":0.2553837817},
{"learn":[3.307462433],"iteration":826,"passed_time":1.213492691,"remaining_time":0.2538503453},
{"learn":[3.304476631],"iteration":827,"passed_time":1.214627897,"remaining_time":0.2523140075},
{"learn":[3.302081967],"iteration":828,"passed_time":1.215757141,"remaining_time":0.2507774079},
{"learn":[3.301491647],"iteration":829,"passed_time":1.216813741,"remaining_time":0.2492269108},
{"learn":[3.300086078],"iteration":830,"passed_time":1.217941383,"remaining_time":0.2476920501},
{"learn":[3.296902693],"iteration":831,"passed_time":1.219182124,"remaining_time":0.2461810058},
{"learn":[3.295639188],"iteration":832,"passed_time":1.220324022,"remaining_time":0.2446507943},
{"learn":[3.295489198],"iteration":833,"passed_time":1.221430324,"remaining_time":0.243114429},
{"learn":[3.295155145],"iteration":834,"passed_time":1.222487164,"remaining_time":0.2415693198},
{"learn":[3.294052338],"iteration":835,"passed_time":1.223805299,"remaining_time":0.2400766376},
{"learn":[3.291428144],"iteration":836,"passed_time":1.22510536,"remaining_time":0.2385808527},
{"learn":[3.290709398],"iteration":837,"passed_time":1.226235636,"remaining_time":0.2370527125},
{"learn":[3.290544339],"iteration":838,"passed_time":1.227318034,"remaining_time":0.2355163331},
{"learn":[3.289975709],"iteration":839,"passed_time":1.228425759,"remaining_time":0.2339858588},
{"learn":[3.289610004],"iteration":840,"passed_time":1.229514238,"remaining_time":0.2324527512},
{"learn":[3.287789503],"iteration":841,"passed_time":1.230731986,"remaining_time":0.230944957},
{"learn":[3.287183593],"iteration":842,"passed_time":1.2318769,"remaining_time":0.2294242862},
{"learn":[3.285756578],"iteration":843,"passed_time":1.233005042,"remaining_time":0.2279014059},
{"learn":[3.285594941],"iteration":844,"passed_time":1.234051393,"remaining_time":0.2263644567},
{"learn":[3.285219444],"iteration":845,"passed_time":1.235287948,"remaining_time":0.2248632907},
{"learn":[3.283285402],"iteration":846,"passed_time":1.236606713,"remaining_time":0.2233775998},
{"learn":[3.283069561],"iteration":847,"passed_time":1.237782634,"remaining_time":0.2218666986},
{"learn":[3.279804214],"iteration":848,"passed_time":1.238926526,"remaining_time":0.2203508898},
{"learn":[3.278314181],"iteration":849,"passed_time":1.240021477,"remaining_time":0.2188273194},
{"learn":[3.277602946],"iteration":850,"passed_time":1.24111796,"remaining_time":0.2173050248},
{"learn":[3.277432017],"iteration":851,"passed_time":1.242192944,"remaining_time":0.215779995},
{"learn":[3.274776401],"iteration":852,"passed_time":1.243399362,"remaining_time":0.2142786708},
{"learn":[3.27447567],"iteration":853,"passed_time":1.244654981,"remaining_time":0.2127864487},
{"learn":[3.274369332],"iteration":854,"passed_time":1.245718603,"remaining_time":0.2112622193},
{"learn":[3.270039549],"iteration":855,"passed_time":1.246819616,"remaining_time":0.2097453559},
{"learn":[3.268898982],"iteration":856,"passed_time":1.247932921,"remaining_time":0.2082315142},
{"learn":[3.268268832],"iteration":857,"passed_time":1.249250875,"remaining_time":0.2067524759},
{"learn":[3.267357814],"iteration":858,"passed_time":1.250380441,"remaining_time":0.2052428895},
{"learn":[3.266431119],"iteration":859,"passed_time":1.251488716,"remaining_time":0.2037307212},
{"learn":[3.266084576],"iteration":860,"passed_time":1.252575392,"remaining_time":0.202216004},
{"learn":[3.263107634],"iteration":861,"passed_time":1.253702803,"remaining_time":0.2007088014},
{"learn":[3.261678033],"iteration":862,"passed_time":1.254836375,"remaining_time":0.199203457},
{"learn":[3.260384586],"iteration":863,"passed_time":1.256012888,"remaining_time":0.1977057323},
{"learn":[3.257544533],"iteration":864,"passed_time":1.257120722,"remaining_time":0.1961980318},
{"learn":[3.257067166],"iteration":865,"passed_time":1.258198632,"remaining_time":0.1946866243},
{"learn":[3.252397152],"iteration":866,"passed_time":1.259295035,"remaining_time":0.1931790539},
{"learn":[3.250673162],"iteration":867,"passed_time":1.26041872,"remaining_time":0.1916765795},
{"learn":[3.249770572],"iteration":868,"passed_time":1.261704274,"remaining_time":0.1901993784},
{"learn":[3.249220449],"iteration":869,"passed_time":1.262927973,"remaining_time":0.1887133753},
{"learn":[3.248496117],"iteration":870,"passed_time":1.264061736,"remaining_time":0.1872146544},
{"learn":[3.247429403],"iteration":871,"passed_time":1.265182285,"remaining_time":0.1857148308},
{"learn":[3.246794946],"iteration":872,"passed_time":1.266268229,"remaining_time":0.184210842},
{"learn":[3.24616788],"iteration":873,"passed_time":1.267511194,"remaining_time":0.1827304468},
{"learn":[3.244976915],"iteration":874,"passed_time":1.26866796,"remaining_time":0.18123828},
{"learn":[3.243186915],"iteration":875,"passed_time":1.269773531,"remaining_time":0.1797396322},
{"learn":[3.241764477],"iteration":876,"passed_time":1.270890162,"remaining_time":0.178243432},
{"learn":[3.24000239],"iteration":877,"passed_time":1.272022883,"remaining_time":0.1767503322},
{"learn":[3.238021541],"iteration":878,"passed_time":1.273113676,"remaining_time":0.1752522808},
{"learn":[3.237977507],"iteration":879,"passed_time":1.27425864,"remaining_time":0.1737625418},
{"learn":[3.237332783],"iteration":880,"passed_time":1.275366414,"remaining_time":0.1722685622},
{"learn":[3.235613438],"iteration":881,"passed_time":1.27650189,"remaining_time":0.1707791645},
{"learn":[3.234829561],"iteration":882,"passed_time":1.277621166,"remaining_time":0.1692884218},
{"learn":[3.23152998],"iteration":883,"passed_time":1.278740623,"remaining_time":0.1677985433},
{"learn":[3.230102275],"iteration":884,"passed_time":1.280075659,"remaining_time":0.166337515},
{"learn":[3.228980199],"iteration":885,"passed_time":1.281249567,"remaining_time":0.164856039},
{"learn":[3.225947357],"iteration":886,"passed_time":1.282389431,"remaining_time":0.1633709196},
{"learn":[3.225399119],"iteration":887,"passed_time":1.283535998,"remaining_time":0.1618874231},
{"learn":[3.223100334],"iteration":888,"passed_time":1.284655193,"remaining_time":0.1604012671},
{"learn":[3.222294685],"iteration":889,"passed_time":1.285861651,"remaining_time":0.1589267209},
{"learn":[3.219342078],"iteration":890,"passed_time":1.287070363,"remaining_time":0.1574530522},
{"learn":[3.218402546],"iteration":891,"passed_time":1.288165434,"remaining_time":0.1559662185},
{"learn":[3.215996238],"iteration":892,"passed_time":1.289282716,"remaining_time":0.1544829234},
{"learn":[3.215834806],"iteration":893,"passed_time":1.290404557,"remaining_time":0.1530009877},
{"learn":[3.215694113],"iteration":894,"passed_time":1.291471967,"remaining_time":0.151513471},
{"learn":[3.214983287],"iteration":895,"passed_time":1.292626148,"remaining_time":0.1500369636},
{"learn":[3.213679792],"iteration":896,"passed_time":1.293751144,"remaining_time":0.1485578237},
{"learn":[3.213009746],"iteration":897,"passed_time":1.294839373,"remaining_time":0.1470752962},
{"learn":[3.210892355],"iteration":898,"passed_time":1.295933322,"remaining_time":0.1455942887},
{"learn":[3.209923581],"iteration":899,"passed_time":1.297040065,"remaining_time":0.1441155627},
{"learn":[3.209101496],"iteration":900,"passed_time":1.298350646,"remaining_time":0.1426600599},
{"learn":[3.208661674],"iteration":901,"passed_time":1.299497142,"remaining_time":0.1411870509},
{"learn":[3.207622193],"iteration":902,"passed_time":1.300582125,"remaining_time":0.1397081574},
{"learn":[3.205828412],"iteration":903,"passed_time":1.301692083,"remaining_time":0.1382327876},
{"learn":[3.205190446],"iteration":904,"passed_time":1.3027738,"remaining_time":0.1367552608},
{"learn":[3.204648891],"iteration":905,"passed_time":1.303919745,"remaining_time":0.1352852716},
{"learn":[3.203744429],"iteration":906,"passed_time":1.305094654,"remaining_time":0.1338189668},
{"learn":[3.202122332],"iteration":907,"passed_time":1.306206767,"remaining_time":0.1323469411},
{"learn":[3.20132131],"iteration":908,"passed_time":1.307292521,"remaining_time":0.1308730686},
{"learn":[3.199832599],"iteration":909,"passed_time":1.308415303,"remaining_time":0.1294037113},
{"learn":[3.197577215],"iteration":910,"passed_time":1.309527346,"remaining_time":0.1279340656},
{"learn":[3.196269864],"iteration":911,"passed_time":1.310822729,"remaining_time":0.1264828949},
{"learn":[3.194372588],"iteration":912,"passed_time":1.311924733,"remaining_time":0.1250136383},
{"learn":[3.193239436],"iteration":913,"passed_time":1.313013392,"remaining_time":0.1235439297},
{"learn":[3.192072931],"iteration":914,"passed_time":1.314136786,"remaining_time":0.1220782807},
{"learn":[3.191674803],"iteration":915,"passed_time":1.315230224,"remaining_time":0.1206106319},
{"learn":[3.191457204],"iteration":916,"passed_time":1.316436091,"remaining_time":0.1191539755},
{"learn":[3.190571136],"iteration":917,"passed_time":1.317571326,"remaining_time":0.1176915564},
{"learn":[3.188173957],"iteration":918,"passed_time":1.318909628,"remaining_time":0.1162477474},
{"learn":[3.18747581],"iteration":919,"passed_time":1.320107049,"remaining_time":0.1147919173},
{"learn":[3.185520312],"iteration":920,"passed_time":1.321288471,"remaining_time":0.113335276},
{"learn":[3.184236151],"iteration":921,"passed_time":1.322529893,"remaining_time":0.1118843077},
{"learn":[3.183958368],"iteration":922,"passed_time":1.323648538,"remaining_time":0.1104235508},
{"learn":[3.183918998],"iteration":923,"passed_time":1.324680843,"remaining_time":0.1089564329},
{"learn":[3.181811262],"iteration":924,"passed_time":1.325832499,"remaining_time":0.1074999323},
{"learn":[3.179830767],"iteration":925,"passed_time":1.326940113,"remaining_time":0.1060405706},
{"learn":[3.177448966],"iteration":926,"passed_time":1.328040745,"remaining_time":0.1045814179},
{"learn":[3.177317076],"iteration":927,"passed_time":1.329225172,"remaining_time":0.1031295392},
{"learn":[3.17630681],"iteration":928,"passed_time":1.330349807,"remaining_time":0.1016736667},
{"learn":[3.174235032],"iteration":929,"passed_time":1.331432486,"remaining_time":0.1002153484},
{"learn":[3.174170885],"iteration":930,"passed_time":1.332602917,"remaining_time":0.09876434078},
{"learn":[3.173921095],"iteration":931,"passed_time":1.33372071,"remaining_time":0.09731009473},
{"learn":[3.172064444],"iteration":932,"passed_time":1.334991517,"remaining_time":0.09586755804},
{"learn":[3.171268114],"iteration":933,"passed_time":1.336128536,"remaining_time":0.09441593511},
{"learn":[3.169383289],"iteration":934,"passed_time":1.337264253,"remaining_time":0.09296489457},
{"learn":[3.168677233],"iteration":935,"passed_time":1.338363512,"remaining_time":0.09151203498},
{"learn":[3.167664516],"iteration":936,"passed_time":1.339434718,"remaining_time":0.09005804404},
{"learn":[3.165762064],"iteration":937,"passed_time":1.340596183,"remaining_time":0.08861083511},
{"learn":[3.164472796],"iteration":938,"passed_time":1.341783014,"remaining_time":0.08716588271},
{"learn":[3.163917318],"iteration":939,"passed_time":1.342865081,"remaining_time":0.08571479241},
{"learn":[3.162579283],"iteration":940,"passed_time":1.343976933,"remaining_time":0.08426635395},
{"learn":[3.159891642],"iteration":941,"passed_time":1.345077324,"remaining_time":0.08281792443},
{"learn":[3.157557949],"iteration":942,"passed_time":1.346333745,"remaining_time":0.08137966432},
{"learn":[3.154362984],"iteration":943,"passed_time":1.347609762,"remaining_time":0.07994295196},
{"learn":[3.150387324],"iteration":944,"passed_time":1.348711395,"remaining_time":0.07849643039},
{"learn":[3.150329169],"iteration":945,"passed_time":1.349742337,"remaining_time":0.07704660275},
{"learn":[3.150183213],"iteration":946,"passed_time":1.350793477,"remaining_time":0.07559879014},
{"learn":[3.148157194],"iteration":947,"passed_time":1.35187893,"remaining_time":0.07415369658},
{"learn":[3.144015194],"iteration":948,"passed_time":1.35321052,"remaining_time":0.07272258851},
{"learn":[3.14379843],"iteration":949,"passed_time":1.354351115,"remaining_time":0.07128163764},
{"learn":[3.142880068],"iteration":950,"passed_time":1.355456896,"remaining_time":0.06983952462},
{"learn":[3.142202947],"iteration":951,"passed_time":1.356562306,"remaining_time":0.06839809949},
{"learn":[3.141330849],"iteration":952,"passed_time":1.357661565,"remaining_time":0.06695707615},
{"learn":[3.140697835],"iteration":953,"passed_time":1.358767006,"remaining_time":0.06551706736},
{"learn":[3.137054095],"iteration":954,"passed_time":1.360037152,"remaining_time":0.06408552025},
{"learn":[3.13617206],"iteration":955,"passed_time":1.361139296,"remaining_time":0.06264657848},
{"learn":[3.135265362],"iteration":956,"passed_time":1.362226282,"remaining_time":0.0612076595},
{"learn":[3.134071497],"iteration":957,"passed_time":1.363353263,"remaining_time":0.05977122863},
{"learn":[3.1324873],"iteration":958,"passed_time":1.364438546,"remaining_time":0.05833366045},
{"learn":[3.131045733],"iteration":959,"passed_time":1.365720443,"remaining_time":0.05690501846},
{"learn":[3.129557536],"iteration":960,"passed_time":1.367013437,"remaining_time":0.05547713219},
{"learn":[3.126889208],"iteration":961,"passed_time":1.368183908,"remaining_time":0.05404468658},
{"learn":[3.125805777],"iteration":962,"passed_time":1.369303264,"remaining_time":0.05261082114},
{"learn":[3.124094863],"iteration":963,"passed_time":1.370440002,"remaining_time":0.05117825735},
{"learn":[3.122520313],"iteration":964,"passed_time":1.372107911,"remaining_time":0.04976557189},
{"learn":[3.122478306],"iteration":965,"passed_time":1.37297549,"remaining_time":0.04832418909},
{"learn":[3.120388137],"iteration":966,"passed_time":1.374159226,"remaining_time":0.04689478226},
{"learn":[3.119581981],"iteration":967,"passed_time":1.375254948,"remaining_time":0.04546297348},
{"learn":[3.119190877],"iteration":968,"passed_time":1.376364796,"remaining_time":0.04403231031},
{"learn":[3.118063177],"iteration":969,"passed_time":1.377662584,"remaining_time":0.04260812114},
{"learn":[3.114165855],"iteration":970,"passed_time":1.37880364,"remaining_time":0.04117951139},
{"learn":[3.113891112],"iteration":971,"passed_time":1.37991429,"remaining_time":0.03975061741},
{"learn":[3.112572413],"iteration":972,"passed_time":1.381152803,"remaining_time":0.03832592567},
{"learn":[3.112228484],"iteration":973,"passed_time":1.38227272,"remaining_time":0.03689845044},
{"learn":[3.111324588],"iteration":974,"passed_time":1.38352633,"remaining_time":0.03547503409},
{"learn":[3.108857495],"iteration":975,"passed_time":1.384715014,"remaining_time":0.03405036921},
{"learn":[3.107550969],"iteration":976,"passed_time":1.385863865,"remaining_time":0.03262524964},
{"learn":[3.106068803],"iteration":977,"passed_time":1.38700943,"remaining_time":0.03120062113},
{"learn":[3.104031028],"iteration":978,"passed_time":1.388104982,"remaining_time":0.02977548991},
{"learn":[3.102797842],"iteration":979,"passed_time":1.389223577,"remaining_time":0.02835150157},
{"learn":[3.101406066],"iteration":980,"passed_time":1.390516245,"remaining_time":0.02693150728},
{"learn":[3.100480211],"iteration":981,"passed_time":1.391633377,"remaining_time":0.02550855476},
{"learn":[3.098333689],"iteration":982,"passed_time":1.392726564,"remaining_time":0.02408581037},
{"learn":[3.097120558],"iteration":983,"passed_time":1.393867861,"remaining_time":0.02266451807},
{"learn":[3.096330771],"iteration":984,"passed_time":1.395220821,"remaining_time":0.02124701757},
{"learn":[3.096162085],"iteration":985,"passed_time":1.396553272,"remaining_time":0.0198293568},
{"learn":[3.094337732],"iteration":986,"passed_time":1.397701472,"remaining_time":0.01840944188},
{"learn":[3.092260094],"iteration":987,"passed_time":1.398808505,"remaining_time":0.01698957698},
{"learn":[3.090392079],"iteration":988,"passed_time":1.399892325,"remaining_time":0.01557008653},
{"learn":[3.089348413],"iteration":989,"passed_time":1.401003897,"remaining_time":0.01415155452},
{"learn":[3.088290614],"iteration":990,"passed_time":1.402356766,"remaining_time":0.0127358334},
{"learn":[3.087412139],"iteration":991,"passed_time":1.403481182,"remaining_time":0.01131839663},
{"learn":[3.085474151],"iteration":992,"passed_time":1.404612851,"remaining_time":0.009901601165},
{"learn":[3.085117898],"iteration":993,"passed_time":1.405677416,"remaining_time":0.008484974339},
{"learn":[3.084458494],"iteration":994,"passed_time":1.406783237,"remaining_time":0.007069262495},
{"learn":[3.083204394],"iteration":995,"passed_time":1.40814905,"remaining_time":0.005655217069},
{"learn":[3.080872503],"iteration":996,"passed_time":1.409409097,"remaining_time":0.004240950142},
{"learn":[3.078992995],"iteration":997,"passed_time":1.410550214,"remaining_time":0.002826753936},
{"learn":[3.0778965],"iteration":998,"passed_time":1.411739329,"remaining_time":0.001413152482},
{"learn":[3.074887149],"iteration":999,"passed_time":1.412912936,"remaining_time":0}
]}